Workbook

Sheet Sheet1
A1: 年 | B1: 2026
A2: 月 | B2: (多项)
A3: 日 | B3: (全部)
A4: 费用类型 | B4: 商务扣款
A6: 发出部门 | B6: 计数项:接收部门 | C6: 求和项:费用金额 | D6: 求和项:费用对应吨数
A7: 珠三角经营部 | B7: 105 | C7: 1412076.2 | D7: 93548.52
A8: 粤西经营部 | B8: 27 | C8: 232206.34 | D8: 20856.46
A9: 广西经营部 | B9: 28 | C9: 202600.82 | D9: 22235.531
A10: 福建经营部 | B10: 66 | C10: 899767.99 | D10: 106154.74
A11: 海南经营部 | B11: 5 | C11: 39266.2 | D11: 2130.36
A12: 总计 | B12: 231 | C12: 2785917.5 | D12: 244925.61
A14: 经营部 | B14: 商扣笔数 | C14: 商扣金额（万元） | D14: 商扣吨数（万吨） | E14: 单吨商扣 （元/吨） | F14: 累计结算量（万吨） | G14: 商扣均摊至结算量（元/吨） | H14: 商扣数量占结算数量比例
A15: 珠三角 | B15: 105 | C15: 141.20762 | D15: 9.354852 | E15: =C15/D15 -> 15.094586 | F15: 110.36 | G15: =C15/F15 -> 1.2795181 | H15: =D15/F15 -> 0.084766691
A16: 粤西 | B16: 27 | C16: 23.220634 | D16: 2.085646 | E16: =C16/D16 -> 11.133545 | F16: 77.93 | G16: =C16/F16 -> 0.29796784 | H16: =D16/F16 -> 0.026763069
A17: 广西 | B17: 28 | C17: 20.260082 | D17: 2.2235531 | E17: =C17/D17 -> 9.11158 | F17: 51.65 | G17: =C17/F17 -> 0.39225715 | H17: =D17/F17 -> 0.043050399
A18: 福建 | B18: 66 | C18: 89.976799 | D18: 10.615474 | E18: =C18/D18 -> 8.4760038 | F18: 59.37 | G18: =C18/F18 -> 1.5155263 | H18: =D18/F18 -> 0.17880199
A19: 海南 | B19: 5 | C19: 3.92662 | D19: 0.213036 | E19: =C19/D19 -> 18.43172 | F19: 43.73 | G19: =C19/F19 -> 0.089792362 | H19: =D19/F19 -> 0.0048716213
A20: 总计 | B20: 231 | C20: 278.59175 | D20: 24.492561 | E20: =C20/D20 -> 11.374546 | F20: 343.04 | G20: =C20/F20 -> 0.81212615 | H20: =D20/F20 -> 0.071398558
C21: 10000
A22: 年 | B22: 2026 | C22: =C20-264.19 -> 14.401754
A23: 月 | B23: (多项)
A24: 费用类型 | B24: (全部)
A25: 发出部门 | B25: (多项)
A27: 扣款原因-清洗 | B27: 求和项:费用金额 | C27: 求和项:费用对应吨数 | F27: 扣款原因 | G27: 扣款金额（元） | H27: 占比
A28: 杂质 | B28: 1332384.7 | C28: 131575.95 | F28: 杂质 | G28: 1332384.7 | H28: =G28/$G$37 -> 0.47825706
A29: 水分 | B29: 804044.5 | C29: 70629.11 | F29: 水分 | G29: 804044.5 | H29: =G29/$G$37 -> 0.2886103
A30: 销售额外费用 | B30: 248896.05 | C30: 10349.282 | F30: 销售额外费用 | G30: 248896.05 | H30: =G30/$G$37 -> 0.089340781
A31: 霉变 | B31: 194483.72 | C31: 23431.145 | F31: 霉变 | G31: 194483.72 | H31: =G31/$G$37 -> 0.069809575
A32: 毒素 | B32: 104388.11 | C32: 7967.19 | F32: 毒素 | G32: 104388.11 | H32: =G32/$G$37 -> 0.037469921
A33: 短重 | B33: 48519.425 | C33: 20.04 | F33: 短重 | G33: 48519.425 | H33: =G33/$G$37 -> 0.017415959
A34: 热损伤 | B34: 45000 | C34: 446.5 | F34: 热损伤 | G34: 45000 | H34: =G34/$G$37 -> 0.016152668
A35: 不完善粒 | B35: 4309.1 | C35: 506.4 | F35: 不完善粒 | G35: 4309.1 | H35: =G35/$G$37 -> 0.0015467436
A36: 容重 | B36: 3891.9 | F36: 容重 | G36: 3891.9 | H36: =G36/$G$37 -> 0.0013969904
A37: 总计 | B37: 2785917.5 | C37: 244925.61 | F37: 总计 | G37: 2785917.5 | H37: =G37/$G$37 -> 1

Sheet 流程
A1: 联系单编号 | B1: 费用发生时间 | C1: 费用申请时间 | D1: 费用类型 | E1: 主题 | F1: 内容 | G1: 销售溢价是否覆盖扣款费用 | H1: 费用原因分类 | I1: 费用金额 | J1: 费用对应吨数 | K1: 费用对应大船名 | L1: 费用对应销售合同号 | M1: 发出部门 | N1: 接收部门 | O1: 发起人 | P1: 复核人1 | Q1: 复核人2 | R1: 复核人3 | S1: 复核人4 | T1: 复核人5 | U1: 费用最终承担方 | V1: 承担方名称/对应合同号 | W1: 复核结果备注 | X1: 扣款原因-清洗 | Y1: 年 | Z1: 月 | AA1: 日
A2: FJSWKK250529 | B2: 45752 | C2: 45782 | D2: 商务扣款 | E2: 关于福建省邵武市华龙饲料有限公司商务扣款说明 | F2: 兹有我司与福建省邵武华龙饲料有限公司签订《粮食销售合同》，合同号：YMFJFZ250015，合同数量3000吨，单价2240元/吨，截止2025年4月5日接货完毕。该合同提货2987.12吨，其中3月26日提货6车共计209.97吨，到货检测指标较差（杂质1.6%，霉变3.6%），经双方协商一致，退货转扣款接收，扣款10元/吨共计2099.7元，折合合同扣款0.7元/吨。 以上扣款，对应内部发运散船航安顺/2507，是否可行，请领导批示。 | H2: 质量问题（霉变、霉味、生虫等） | I2: 2099.7 | J2: 209.97 | M2: 福建经营部 | N2: 饲料原料部、风险管理部、财务部 | O2: 林玉婷 | P2: 福建经营部 | Q2: 大区品种线 | U2: 供应商 | Y2: =YEAR(C2) -> 2025 | Z2: =MONTH(C2) -> 5 | AA2: =DAY(C2) -> 5
B3: 5/13-5/15 | C3: 45817 | D3: 商务扣款 | E3: JZXYMGXXJ250003广西福祺保毒素箱子毒素超标扣款说明 | F3: 该批保毒素箱子21个，总计554.97吨，计划交付广西福祺饲料有限公司保毒素合同（合同号：JZXYMGXXJ250003），4月21日和4月25日从北方发出，5月3日至5月8日抵达贵港港（运单号：AUVTNTW250238777、ASNCLTL250258834），计划号YHSZ-25-032021。5月13日至5月15日全部提完。到厂检测毒素超标，7个箱子毒素指标在1100-1300ppb之间，14个箱子毒素指标在1400-1900ppb之间。我部及时与玉米品种线联系并向大区反映情况，后经大区协调，现场取样邮至北良港检测公司董乾仕复检，四个集装箱（ATHU1009372、ATHU1078877、FBIU0022667、FBIU0003991）分两个样品毒素检测结果值为1491ppb和1729ppb。下游客户要求商扣50元/吨，经我司协商最终扣20元/吨，总计11099.4元。 | H3: 品质不达标（容重、水分、毒素、蛋白等） | I3: 11099.4 | J3: 554.97 | L3: JZXYMGXXJ250003 | M3: 广西经营部 | O3: 侯霄 | P3: 广西经营部 | Q3: 大区品种线 | Y3: =YEAR(C3) -> 2025 | Z3: =MONTH(C3) -> 6 | AA3: =DAY(C3) -> 9
B4: 2025/5/17、6/2 | C4: 45826 | D4: 商务扣款 | E4: 关于龙岩华龙扣款说明 | F4: 我司与福建省龙岩市华龙饲料有限公司于2025年05月09日签署生效的《粮食销售合同》（合同编号：JZXYMFJZZ250004)，合同数量480吨，合同单价2420元/吨，截止至2025年06月04日，该合同累计提货471.075吨，客户于2025年5月17日接收玉米，检测呕吐毒素超标；检测容重未达标，合计产生扣款2704.76元，整批次提货471.075吨，折单吨扣款5.74元/吨 | H4: 品质不达标（容重、水分、毒素、蛋白等） | I4: 2704.76 | J4: 471.075 | M4: 福建经营部 | N4: 饲料原料部 | O4: 陈静文 | P4: 福建经营部 | Q4: 大区品种线 | Y4: =YEAR(C4) -> 2025 | Z4: =MONTH(C4) -> 6 | AA4: =DAY(C4) -> 18
B5: 2025/5/16、6/4 | C5: 45826 | D5: 商务扣款 | E5: 关于龙岩鑫华港饲料有限公司扣款说明 | F5: 我司与龙岩鑫华港饲料有限公司于2025年05月09日签署生效的《粮食销售合同》（合同编号：JZXYMFJZZ250005)，合同数量420吨，合同单价2420元/吨，截止至2025年05月20日，该合同累计提货414.4吨，检测有呕吐毒素超标；检测容重未达标，以上情况合计产生扣款2204.80元，整批次提货414.4吨，折单吨扣款5.32元/吨 | H5: 品质不达标（容重、水分、毒素、蛋白等） | I5: 2204.8 | J5: 414.4 | M5: 福建经营部 | N5: 饲料原料部 | O5: 陈静文 | P5: 福建经营部 | Q5: 大区品种线 | Y5: =YEAR(C5) -> 2025 | Z5: =MONTH(C5) -> 6 | AA5: =DAY(C5) -> 18
B6: 45811 | C6: 45826 | D6: 商务扣款 | E6: 关于武平鑫龙港饲料有限公司扣款说明 | F6: 我司与武平鑫龙港饲料有限公司于2025年05月09日签署生效的《粮食销售合同》（合同编号：JZXYMFJZZ250006)，合同数量220吨，合同单价2420元/吨，截止至2025年05月18日，该合同累计提货221.905吨，检测容重未达标，合计扣款1071.40元，整批次提货221.905吨，折单吨扣款4.83元/吨 | H6: 品质不达标（容重、水分、毒素、蛋白等） | I6: 1071.4 | J6: 221.905 | M6: 福建经营部 | N6: 饲料原料部 | O6: 陈静文 | P6: 福建经营部 | Q6: 大区品种线 | Y6: =YEAR(C6) -> 2025 | Z6: =MONTH(C6) -> 6 | AA6: =DAY(C6) -> 18
A7: JZXYMFJZZ250004-lxd01 | B7: 45866 | C7: 45866 | D7: 商务扣款 | E7: 福建省龙岩市华龙饲料有限公司 | I7: 11255 | J7: 11255 | K7: 玉米出险对应扣款 | L7: JZXYMFJZZ250004 | M7: 福建经营部 | N7: 饲料原料部 | O7: 陈静文 | P7: 福建经营部 | Q7: 大区品种线 | Y7: =YEAR(C7) -> 2025 | Z7: =MONTH(C7) -> 7 | AA7: =DAY(C7) -> 28
A8: YMFJZZ250152-lxd01 | B8: 45880 | C8: 45880 | D8: 商务扣款 | E8: 双胞胎（集团）股份有限公司 | I8: 1782 | J8: 1782 | K8: 呕吐毒素超标 | L8: YMFJZZ250152 | M8: 福建经营部 | N8: 饲料原料部 | O8: 陈静文 | P8: 福建经营部 | Q8: 大区品种线 | Y8: =YEAR(C8) -> 2025 | Z8: =MONTH(C8) -> 8 | AA8: =DAY(C8) -> 11
A9: YMFJZZ250142-lxd01 | B9: 45889 | C9: 45889 | D9: 商务扣款 | E9: 漳州温氏农牧有限公司 | I9: 10655.1 | J9: 10655.1 | K9: 杂质超标 | L9: YMFJZZ250142 | M9: 福建经营部 | N9: 饲料原料部 | O9: 陈静文 | P9: 福建经营部 | Q9: 大区品种线 | Y9: =YEAR(C9) -> 2025 | Z9: =MONTH(C9) -> 8 | AA9: =DAY(C9) -> 20
A10: YMFJZZ250173-lxd01 | B10: 45889 | C10: 45889 | D10: 商务扣款 | E10: 正大原料供应有限公司 | I10: 4698.52 | J10: 4698.52 | K10: 杂质和破碎超标 | L10: YMFJZZ250173 | M10: 福建经营部 | N10: 饲料原料部 | O10: 陈静文 | P10: 福建经营部 | Q10: 大区品种线 | Y10: =YEAR(C10) -> 2025 | Z10: =MONTH(C10) -> 8 | AA10: =DAY(C10) -> 20
A11: YMFJZZ250130-lxd01 | B11: 45888 | C11: 45888 | D11: 商务扣款 | E11: 漳州海大饲料有限公司 | I11: 936 | J11: 936 | K11: 杂质超标 | L11: YMFJZZ250130 | M11: 福建经营部 | N11: 饲料原料部 | O11: 陈静文 | P11: 福建经营部 | Q11: 大区品种线 | Y11: =YEAR(C11) -> 2025 | Z11: =MONTH(C11) -> 8 | AA11: =DAY(C11) -> 19
A12: YHSZFJ250613XMX0001-lxd01 | B12: 45888 | C12: 45888 | D12: 商务扣款 | E12: 四川新希望贸易有限公司 | I12: 311.4 | J12: 311.4 | K12: 容重不达标 | L12: YHSZFJ250613XMX0001 | M12: 福建经营部 | N12: 饲料原料部 | O12: 陈静文 | P12: 福建经营部 | Q12: 大区品种线 | Y12: =YEAR(C12) -> 2025 | Z12: =MONTH(C12) -> 8 | AA12: =DAY(C12) -> 19
A13: YMZSJJY250170 | B13: 46001 | C13: 46002 | D13: 商务扣款 | E13: 丰顺县海新饲料有限公司 | F13: 丰顺县海新饲料有限公司，2025年11月12日签订《粮食销售合同(赊销)》(合同编号:YMZSJJY250170)，数量 500 吨，单价 2320 元/吨，该合同已累计交货 496吨，(其中 11月 20日3 车车号:赣 C5615D，重量 31.7吨，车号:粤 V05263,重量 33.77 吨，车号:粤 VN1708，重量 34.84吨，合计:100.31 吨)到货玉米经检验杂质 1.2%杂质和破碎粒超出合同约定指标(杂质≤1%),不符合客户接受指标。针对该批次到厂不合格玉米，经双方友好协商处理后，退货转扣款接收。经双方友好协商处理后，退货转扣款接收，合计扣款 1003.1元 折合10元/吨。 | H13: 品质不达标（容重、水分、毒素、蛋白等） | I13: 1003.1 | J13: 100.31 | K13: 恒通达/2529、锦航力鹏/2528 | L13: YMZSJJY250170 | M13: 珠三角经营部 | N13: 饲料原料部 | O13: 蚁毓霖 | P13: 珠三角经营部 | Q13: 大区品种线 | Y13: =YEAR(C13) -> 2025 | Z13: =MONTH(C13) -> 12 | AA13: =DAY(C13) -> 11
A14: YMZSIIY250177 | B14: 46001 | C14: 46002 | D14: 商务扣款 | E14: 丰顺县海新饲料有限公司 | F14: 丰顺县海新饲料有限公司,于2025年11月20日签订《粮食销售合同》(合同编号:YMZSIIY250177)，数量 500 吨，单价 2340 元/吨,该合同已累计交货 495.46吨，(其中12月2日4车车号:粤 BGT302,重量 34.97 吨，车号:赣C4M573，重量 36.5吨，车号:粤D28948，重量 38.6吨，车号:赣C7N367,重量 43.52 吨合计:153.59 吨)到货玉米经检验杂质 1.2%杂质和破碎粒超出合同约定指标(杂质≤19)，不符合客户接受指标。针对该批次到厂不合格玉米，经双方友好协商处理后，退货转扣款接收。 | H14: 品质不达标（容重、水分、毒素、蛋白等） | I14: 1535.9 | J14: 153.59 | K14: 鑫顺弘盛/2537 | L14: YMZSIIY250177 | M14: 珠三角经营部 | N14: 饲料原料部 | O14: 蚁毓霖 | P14: 珠三角经营部 | Q14: 大区品种线 | Y14: =YEAR(C14) -> 2025 | Z14: =MONTH(C14) -> 12 | AA14: =DAY(C14) -> 11
A15: JZXYMZSJJM25047 玉米扣款—保险 | B15: 45925 | C15: 46000 | D15: 商务扣款 | E15: 广东粮品农产品经验有限公司 | F15: 经双方友好协商处理后，退货转扣款接收，合计扣款 1535.9元 折合10 元/吨。 | H15: 包装破损、水湿、短重等 | I15: 23574.6 | J15: 46.19 | K15: 箱子进水 | L15: JZXYMZSJJM25047 | M15: 珠三角经营部 | N15: 饲料原料部 | O15: 汤妮 | P15: 珠三角经营部 | Q15: 大区品种线 | Y15: =YEAR(C15) -> 2025 | Z15: =MONTH(C15) -> 12 | AA15: =DAY(C15) -> 9
A16: JZXYMZSJJM25047 玉米扣款 | B16: 45925 | C16: 46000 | D16: 商务扣款 | E16: 广东粮品农产品经验有限公司 | F16: 广东粮品农产品经验有限公司，于2025 年9月25 日签订的《粮食销售合同》合同编号:JZXYMZSJJM25047)合同数量 351 吨,合同单价 2460 元/吨，计划号 YHSZ-25-072128，运单号 AYWWCRX250607901A，共13 柜，截止到9月 29 日该合同下货物已提货完毕。其中 6柜玉米分别存在霉变和生虫的现象: (1)TAHU1162503和ATHU1046083，26.73和7.78，霉变超标，扣款 50 元/吨 (2)ATHU1046083、ATHU1265939、ATHU1303556、ATHU1246651和ATHU1103202卸重分别为 26.86、26.85、26.9和 27.21，存在生虫现象，扣款 50 元/吨合计扣款金额为:7965.9元。 | H16: 质量问题（霉变、霉味、生虫等） | I16: 7965.9 | J16: 142.33 | L16: JZXYMZSJJM25047 | M16: 珠三角经营部 | N16: 饲料原料部 | O16: 汤妮 | P16: 珠三角经营部 | Q16: 大区品种线 | Y16: =YEAR(C16) -> 2025 | Z16: =MONTH(C16) -> 12 | AA16: =DAY(C16) -> 9
A17: YMZSJQY250219 | B17: 45980 | C17: 46002 | D17: 商务扣款 | E17: 广东泰德饲料有限公司扣款 | F17: 广东泰德饲料有限公司于11月12日签订国产内贸合同(合同号YMZSJQY250219，合同量1000 吨，单价 2320 元/吨)，该合同为吉林经营部与我司珠三角经营部协同发往英德站的保1000 毒素玉米，客户于 11月19 日开始提货其中，有6车玉米呕吐毒素超出合同第二条:质量标准中:呕吐毒素<1000ug/kg的约定，具体明细如下:经过双方友好协商，决定对该批次不合格的玉米进行扣款处理，经沟通，毒素超示的部分扣款一共 5451.6 元由上游吉林经营部承担。 | H17: 质量问题（霉变、霉味、生虫等） | I17: 5451.6 | K17: 吉林经营部发运 | L17: YMZSJQY250219 | M17: 珠三角经营部 | N17: 饲料原料部 | O17: 董典昊 | P17: 珠三角经营部 | Q17: 大区品种线 | Y17: =YEAR(C17) -> 2025 | Z17: =MONTH(C17) -> 12 | AA17: =DAY(C17) -> 11
A18: YMZSJQY250205 | B18: 45982 | C18: 46002 | D18: 商务扣款 | E18: 郴州大北农饲料有限公司扣款 | F18: 郴州大北农饲料科技有限公司于 11月11日签订国产内贸合同(合同号YMZSJQY250205，合同量 800 吨，单价 2250 元/吨)，客户于 11月21 日开始提货我司麻涌港:国家能源 610/2511 轮玉米，现有部分玉米到厂后，出现杂质超标情况，明细如下:除湘 LB8781 提货杂质为 1.19%扣款 10 元/吨外，其余车辆杂质综合达到2.21%，该合同第二条质量标准约定:杂质≤1.0%，经过双方友好协商，决定对该批次不合格的玉米进行扣款处理，请领导审批。经沟通，该批次货物扣款共计:6649元。 | H18: 质量问题（霉变、霉味、生虫等） | I18: 6649 | K18: 国家能源 610/2511 | L18: YMZSJQY250205 | M18: 珠三角经营部 | N18: 饲料原料部 | O18: 董典昊 | P18: 珠三角经营部 | Q18: 大区品种线 | Y18: =YEAR(C18) -> 2025 | Z18: =MONTH(C18) -> 12 | AA18: =DAY(C18) -> 11
A19: YMZSJQY250179 | B19: 45985 | C19: 46002 | D19: 商务扣款 | E19: 英德天农饲料有限公司扣款 | F19: 英德天农饲料有限公司，2025 年11月15日签订的《粮食销售合同》(合同编号:YMZSJQY250179)合同数量 1000 吨，合同单价 2310 元/吨，根据签订的《粮食销售合同》第二条款约定的质量标准，交付的玉米标准应当符合如下约定:“容重2685g儿L，水分≤15.0%，杂质≤1.0%，霉变粒≤2.0%，呕吐毒素≤1000ug/kg，”。客户提货我司从北方发运散改基玉米，2025年11月16日至24日到厂柜号:5588171、0809541、330766、6457540、0733826，共受委托承运供方玉米 120.01 吨，合同单价 2310 元/吨，到需方英德天农工厂，经品管技术部门抽样不达合同约定标准，经供需双方友好协商，需方同意2车玉米折价收货。其中 5588171、0809541柜毒素超标:1493.99、1147.01，双方友好协商折价 30元/吨，结算即 2280 元/吨为准;330766柜毒素超标:1081.93，双方友好协商折价5元/吨，结算即 2305 元/吨为准;6457540、0733826柜毒素超标:1066.21、1024.4，双方友好协商折价5元/吨，结算即 2305 元/吨为准。合计扣款1344.8元 | H19: 质量问题（霉变、霉味、生虫等） | I19: 1344.8 | K19: 吉林经营部发运 | L19: YMZSJQY250179 | M19: 珠三角经营部 | N19: 饲料原料部 | O19: 董典昊 | P19: 珠三角经营部 | Q19: 大区品种线 | Y19: =YEAR(C19) -> 2025 | Z19: =MONTH(C19) -> 12 | AA19: =DAY(C19) -> 11
A20: JCYMZSJQY250029-1 | B20: 45988 | C20: 46020 | D20: 商务扣款 | E20: 关于安佑集团结算扣价 | F20: 苏州穗满德国际贸易有限公司，2025年11月13日签订的《粮食销售合同》(合同编号:JCYMZSJQY250029-1)合同数量1500吨，合同单价2302元/吨，提货新沙港国远86、中瑞祥79，三车到厂检测霉变为2.5%超出合同约定的标准，合计98.38吨，申请每吨扣款20元，扣款20元*98.38吨=1967.6元。 | H20: 品质不达标（容重、水分、毒素、蛋白等） | I20: 1967.6 | J20: 98.38 | K20: 国远86、中瑞祥79 | L20: JCYMZSJQY250029-1 | M20: 珠三角经营部 | N20: 饲料原料部 | O20: 董典昊 | Y20: =YEAR(C20) -> 2025 | Z20: =MONTH(C20) -> 12 | AA20: =DAY(C20) -> 29
A21: YMYXMM250768 | B21: 45979 | C21: 46002 | D21: 商务扣款 | E21: 双胞胎（集团）股份有限公司扣款 | F21: 客户在对应外采船“锦富航 69/2530”轮提货过程中，反馈 706.74 吨玉米感官有黑粒，霉变超标，存在质量不合格问题，经饲料厂人员取样检测并复查，霉变达 2.3%，合同约定质量标准：霉变粒≤2%，不符合合同规定。经我部与客 户多次协商，秉承长期友好合同原则，共申请扣款 14134.8 元，单吨扣款 20 元/吨 | H21: 质量问题（霉变、霉味、生虫等） | I21: 14134.8 | J21: 706.74 | K21: 锦富航 69/2530 | L21: YMYXMM250768 | M21: 粤西经营部 | N21: 饲料原料部 | O21: 余诗莹 | P21: 饲料原料部 | Q21: 大区品种线 | Y21: =YEAR(C21) -> 2025 | Z21: =MONTH(C21) -> 12 | AA21: =DAY(C21) -> 11
A22: 关于JZXYMZSJJM25048玉米扣款 | B22: 45933 | C22: 46002 | D22: 商务扣款 | E22: 鹤山市广顺饲料有限公司 | F22: 鹤山市广顺饲料有限公司，于 2025 年 09 月 28 日签订的《粮食销售合同》合同编号:JZXYMZSJJM25048)合同数量 150 吨,合同单价 2400 元/吨，计划号JZXYMSZCG250076 和YHSZ-25-072128，运单号Q085591683和AYWWCRX250607901A，共6柜，截止到 10月 3日该合同下货物已提货完毕。 1、柜号 XYLU1060398，卸厂数 26.42 吨，水湿发霉，发热结块严重，价格按 1700 元/吨结算，已报保险，保险承担8800元。 2、柜号 00CU0908616和 ATHU1168857,卸厂数分别为 26.403和 9.9(半柜)，发热发霉价格按 2330 元/吨结算，其中00CU0908616已报保险，保险承担9920元。合计扣款金额为:18494+2541.21=21035.21元，已报保险，保险承担18720元. | H22: 包装破损、水湿、短重等 | I22: 21035.21 | J22: 62.723 | L22: JZXYMZSJJM25048 | M22: 珠三角经营部 | N22: 饲料原料部 | O22: 汤妮 | P22: 珠三角经营部 | Q22: 大区品种线 | Y22: =YEAR(C22) -> 2025 | Z22: =MONTH(C22) -> 12 | AA22: =DAY(C22) -> 11
A23: YMYXYJ250166 | B23: 46002 | C23: 46002 | D23: 商务扣款 | E23: 阳江双胞胎饲料有限公司 | F23: 我司于2025年9月18日与阳江双胞胎饲料有限公司签订了玉米内贸合同YMYXYJ250166，签订主体为中粮贸易（深圳）有限公司。合同总量为1000吨，单价为2440元/吨，实际执行量为949.18吨。具体提货情况如下：在锦航万盛/2522船上提货473.68吨，在鑫晟奋发/2523船上提货475.50吨。合同约定标准：呕吐毒素含量不得超过1000PPB。 在2025年9月21日至2025年10月9日期间，客户提取了一批玉米（猪料），经检测，呕吐毒素含量在1131至1452之间，不符合合同约定的标准。考虑到双方后期的长期友好合作，对该批货物进行20元/吨的折价处理，总计折价金额为18938.6元。此次扣款已从预留的20000元中扣除。 | H23: 品质不达标（容重、水分、毒素、蛋白等） | I23: 18983.6 | J23: 949.18 | K23: 鑫晟奋发/2523、锦航万盛/2522 | L23: YMYXYJ250166 | M23: 粤西经营部 | N23: 饲料原料部 | O23: 刘佳莹 | P23: 饲料原料部 | Q23: 大区品种线 | Y23: =YEAR(C23) -> 2025 | Z23: =MONTH(C23) -> 12 | AA23: =DAY(C23) -> 11
A24: 茂名海航 YMYXMM250260 质量扣款的情况说明 | B24: 45895 | C24: 45988 | D24: 商务扣款 | E24: 茂名海航饲料有限公司 | F24: 在外采大船“天台 19/2518”轮提货过程中，160.05 吨存在有异常发热、有霉味、杂质超标的质量问题，杂 质达 3.7%，不符合同规定。经我司业务人员核实，检测结果确实存在。秉承长期友好合同原则，经我部与客 户多次友好协商后，做扣价 30 元/吨处理，申请扣款金额合计 4801.5 元，该船质量问题已报备饲料原料部。 由于该合同已经结算，申请在 YMYXMM250747 做抵扣 | H24: 品质不达标（容重、水分、毒素、蛋白等） | I24: 4801.5 | J24: 160.05 | K24: 天台 19/2518 | L24: YMYXMM250260 | M24: 粤西经营部 | N24: 饲料原料部 | O24: 余诗莹 | P24: 饲料原料部 | Q24: 大区品种线 | Y24: =YEAR(C24) -> 2025 | Z24: =MONTH(C24) -> 11 | AA24: =DAY(C24) -> 27
A25: YMFJFZ250147 | B25: 40703 | C25: 46000 | D25: 商务扣款 | E25: 双胞胎（集团）股份有限公司 | F25: 兹有我司与双胞胎（集团）股份有限公司签订《粮食销售合同》（合同号：YMFJFZ250147）合同数量1000吨，单价2310元/吨，合同约定呕吐毒素≤1000ppb。该合同实际接货1019.74吨，在提货过程中,出现部分车次呕吐毒素超标问题,扣款金额为 5264.4元,折合5.16元/吨。该批次提货对应军航码头散船瑞生16/2528轮（挑选出货），该批次销售为双胞胎集团下属工厂屏南双胞胎饲料有限公司，为首次开发工厂，客户扣款已在后续合同中以保毒素玉米价格加价给我司（YMFJFZ250188合同，1000吨，2425元/吨，加价16元/吨）。 | Y25: =YEAR(C25) -> 2025 | Z25: =MONTH(C25) -> 12 | AA25: =DAY(C25) -> 9
A26: YMFJZZ250287 | B26: 45983 | C26: 46005 | D26: 商务扣款 | E26: 福建湘大骆驼饲料有限公司 | Y26: =YEAR(C26) -> 2025 | Z26: =MONTH(C26) -> 12 | AA26: =DAY(C26) -> 14
A27: JZXYMGXXJ250067 | B27: 45975 | C27: 46005 | D27: 商务扣款 | E27: 广西南宁央卓粮食贸易有限公司 | F27: 客户名：广西南宁央卓粮食贸易有限公司,合同号：JZXYMGXXJ250067,单价：2275元/吨，签订指标：容重 ≥710g/l，水分≤14.5%，霉变≤2%，热损≤1%，杂质≤1%，不完善≤8%，呕吐毒素≤1000ppb，计划号： YHSZ-25-092334，运单号：AWKTRTT250772047、APSFCQC250784002，11月14日开始提货，在交货时， 下反馈毒素超标，经我放人员核实并重新取样邮寄至北良华正检测（检测结果如附件），客户反馈共计16柜（444.08吨）毒素超标，每吨扣款60元/吨，经我部与客户多次友好协商后，对其中14 柜（389.55吨）做扣价 20 元/吨处理，即本合同扣款389.55吨*20元/吨=7791元， | H27: 品质不达标（容重、水分、毒素、蛋白等） | I27: 7791 | J27: 389.55 | L27: JZXYMGXXJ250067 | M27: 广西经营部 | N27: 饲料原料部 | O27: 朱雪语 | Y27: =YEAR(C27) -> 2025 | Z27: =MONTH(C27) -> 12 | AA27: =DAY(C27) -> 14
A28: YHYMGXXS250904003 | B28: 9月13 | C28: 46006 | D28: 商务扣款 | E28: 广西柳州桂柳牧业有限公司 | F28: 合同号：YHYMGXXS250904003，客户名：广西柳州桂柳牧业有限公司，合同数量：700吨，单价：2390元/ 吨 , 提货数量：692.22吨，该批粮源为扬翔退货货源，在发运时，船运已反馈杂质大、破碎高，到达白沙港 时，我部人员朱雪语，现场检查，情况属实，并伴有发霉发热现场。退回白沙库（提珠三角“国远705”船，驳 船名：贵港兴泰82）另行销售，在销售时按照市场行情正价销售，于9月5日-9月13日陆续提货，到厂收货时，客 户反馈其中472.15吨出现发霉，发热等现象，客户提出该部分每吨扣款60元接收，经过跟客户友好协商，每吨按 照30元进行扣款让步接收，即472.15元*30元/吨=14,164.5元 | H28: 质量问题（霉变、霉味、生虫等） | I28: 14164.5 | J28: 472.15 | K28: 国远705 | L28: YHYMGXXS250904003 | M28: 广西经营部 | N28: 饲料原料部 | O28: 朱雪语 | Y28: =YEAR(C28) -> 2025 | Z28: =MONTH(C28) -> 12 | AA28: =DAY(C28) -> 15
A29: YMZSJDG250122 | B29: 45867 | C29: 46006 | D29: 商务扣款 | E29: 广州顺泽粮食贸易有限公司 | F29: 一体化计划号:YHSZ-25-062402，YHSZ-25-062403，YHSZ-25-062404共销售广州顺泽粮食贸易有限公司115 柜，2025年7月11日签订的《粮食销售合同》(合同编号:YMZSJDG250122)合同数量 3000吨，合同单价 2440 元/吨，结算数量 3054.678 吨。该合同交货过程中 102 柜质量问题产生扣款合计扣款91846.45 元: 其中 82 柜发热有霉味扣款 30 元/吨让步降价处理;1柜发热发霉结块扣款 80 元/吨让步接收，1 柜箱内有垃圾，水湿结块，扣款 40 元/吨降价处理,1柜发热发霉,有虫扣款 60 元/吨让步接收,1柜容重 702ppb复测 696ppb,不达标扣款 10 元/吨，1柜容重 695ppb 不达标扣款 20 元/吨。 | H29: 发霉发热 | I29: 91846.45 | K29: 天隆河/299S、延展228/043S、昌盛集 9/047S | L29: YMZSJDG250122 | M29: 珠三角经营部 | N29: 饲料原料部 | O29: 林佳琦 | Y29: =YEAR(C29) -> 2025 | Z29: =MONTH(C29) -> 12 | AA29: =DAY(C29) -> 15
B30: 46001 | C30: 46006 | D30: 商务扣款 | E30: 关于南宁海大杂质超标扣款 | F30: 在珠三角提货，因交货为筒仓货物，交货时均为筒仓底部货物，杂质偏大 | H30: 杂质超标 | I30: 29949.34 | J30: 2994.934 | K30: 东星海泰/077 | L30: /YMGXQZ250275/YMGXQZ250276 | M30: 广西经营部 | N30: 饲料原料部 | O30: 宁昕 | Y30: =YEAR(C30) -> 2025 | Z30: =MONTH(C30) -> 12 | AA30: =DAY(C30) -> 15
A31: YHYMZSJXS251113002 | B31: 45987 | C31: 46006 | D31: 商务扣款 | E31: 广州顺泽粮食贸易有限公司 | F31: 该合同交货过程中1柜箱号:OOLU2987138 箱底未干0.3 吨粘底卸不下来客户折价 1732 元/吨，扣款 519.6 元让步接收 | H31: 质量问题（水湿粘底） | I31: 519.6 | J31: 0.3 | K31: TIAN XIU HE 340S | L31: YHYMZSJXS251113002 | M31: 珠三角经营部 | N31: 饲料原料部 | O31: 林佳琦 | Y31: =YEAR(C31) -> 2025 | Z31: =MONTH(C31) -> 12 | AA31: =DAY(C31) -> 15
A32: YMYXMM250558 | B32: 45943 | C32: 46006 | D32: 商务扣款 | E32: 关于潘钟明、余剑玲、黄东宇、林雪清、许忠炯、广东双谷、双胞胎陈粮合同折价的情况说明 | F32: 因无陈粮库存交货，经多次反复沟通协商，以下打包厂、饲料厂陈粮合同剩余未提量在”佳升56/2521“、“锦江河/2519”、“海腾炜业6/2508”、“锦江河/2521”、“利泰朝阳/2524”新船执行，申请在新船执行量折价30元/吨，以下为具体明细 | H32: 品质不达标（容重、水分、毒素、蛋白等） | I32: 9482.4 | J32: 316.08 | K32: 佳升56/2521 | L32: YMYXMM250558 | M32: 粤西经营部 | N32: 饲料原料部 | O32: 余诗莹 | P32: 饲料原料部 | Q32: 大区品种线 | Y32: =YEAR(C32) -> 2025 | Z32: =MONTH(C32) -> 12 | AA32: =DAY(C32) -> 15
A33: YMYXMM250554 | B33: 45943 | C33: 46006 | D33: 商务扣款 | E33: 关于潘钟明、余剑玲、黄东宇、林雪清、许忠炯、广东双谷、双胞胎陈粮合同折价的情况说明 | F33: 因无陈粮库存交货，经多次反复沟通协商，以下打包厂、饲料厂陈粮合同剩余未提量在”佳升56/2521“、“锦江河/2519”、“海腾炜业6/2508”、“锦江河/2521”、“利泰朝阳/2524”新船执行，申请在新船执行量折价30元/吨，以下为具体明细 | H33: 品质不达标（容重、水分、毒素、蛋白等） | I33: 7481.1 | J33: 249.37 | K33: 佳升56/2521 | L33: YMYXMM250554 | M33: 粤西经营部 | N33: 饲料原料部 | O33: 余诗莹 | P33: 饲料原料部 | Q33: 大区品种线 | Y33: =YEAR(C33) -> 2025 | Z33: =MONTH(C33) -> 12 | AA33: =DAY(C33) -> 15
A34: YMYXMM250602 | B34: 45947 | C34: 46006 | D34: 商务扣款 | E34: 关于潘钟明、余剑玲、黄东宇、林雪清、许忠炯、广东双谷、双胞胎陈粮合同折价的情况说明 | F34: 因无陈粮库存交货，经多次反复沟通协商，以下打包厂、饲料厂陈粮合同剩余未提量在”佳升56/2521“、“锦江河/2519”、“海腾炜业6/2508”、“锦江河/2521”、“利泰朝阳/2524”新船执行，申请在新船执行量折价30元/吨，以下为具体明细 | H34: 品质不达标（容重、水分、毒素、蛋白等） | I34: 14221.2 | J34: 474.04 | K34: 佳升56/2521、锦江河/2519、海腾炜业6/2508、锦江河/2521、利泰朝阳/2524 | L34: YMYXMM250602 | M34: 粤西经营部 | N34: 饲料原料部 | O34: 余诗莹 | P34: 饲料原料部 | Q34: 大区品种线 | Y34: =YEAR(C34) -> 2025 | Z34: =MONTH(C34) -> 12 | AA34: =DAY(C34) -> 15
A35: YMYXMM250553 | B35: 45943 | C35: 46006 | D35: 商务扣款 | E35: 关于潘钟明、余剑玲、黄东宇、林雪清、许忠炯、广东双谷、双胞胎陈粮合同折价的情况说明 | F35: 因无陈粮库存交货，经多次反复沟通协商，以下打包厂、饲料厂陈粮合同剩余未提量在”佳升56/2521“、“锦江河/2519”、“海腾炜业6/2508”、“锦江河/2521”、“利泰朝阳/2524”新船执行，申请在新船执行量折价30元/吨，以下为具体明细 | H35: 品质不达标（容重、水分、毒素、蛋白等） | I35: 8663.4 | J35: 288.78 | K35: 佳升56/2521、锦江河/2519 | L35: YMYXMM250553 | M35: 粤西经营部 | N35: 饲料原料部 | O35: 余诗莹 | P35: 饲料原料部 | Q35: 大区品种线 | Y35: =YEAR(C35) -> 2025 | Z35: =MONTH(C35) -> 12 | AA35: =DAY(C35) -> 15
A36: YMYXMM250596 | B36: 45950 | C36: 46006 | D36: 商务扣款 | E36: 关于潘钟明、余剑玲、黄东宇、林雪清、许忠炯、广东双谷、双胞胎陈粮合同折价的情况说明 | F36: 因无陈粮库存交货，经多次反复沟通协商，以下打包厂、饲料厂陈粮合同剩余未提量在”佳升56/2521“、“锦江河/2519”、“海腾炜业6/2508”、“锦江河/2521”、“利泰朝阳/2524”新船执行，申请在新船执行量折价30元/吨，以下为具体明细 | H36: 品质不达标（容重、水分、毒素、蛋白等） | I36: 14747.1 | J36: 491.57 | K36: 锦江河/2519 | L36: YMYXMM250596 | M36: 粤西经营部 | N36: 饲料原料部 | O36: 余诗莹 | P36: 饲料原料部 | Q36: 大区品种线 | Y36: =YEAR(C36) -> 2025 | Z36: =MONTH(C36) -> 12 | AA36: =DAY(C36) -> 15
A37: YMYXMM250582 | B37: 45943 | C37: 46006 | D37: 商务扣款 | E37: 关于潘钟明、余剑玲、黄东宇、林雪清、许忠炯、广东双谷、双胞胎陈粮合同折价的情况说明 | F37: 因无陈粮库存交货，经多次反复沟通协商，以下打包厂、饲料厂陈粮合同剩余未提量在”佳升56/2521“、“锦江河/2519”、“海腾炜业6/2508”、“锦江河/2521”、“利泰朝阳/2524”新船执行，申请在新船执行量折价30元/吨，以下为具体明细 | H37: 品质不达标（容重、水分、毒素、蛋白等） | I37: 11266.2 | J37: 375.54 | K37: 佳升56/2521 | L37: YMYXMM250582 | M37: 粤西经营部 | N37: 饲料原料部 | O37: 余诗莹 | P37: 饲料原料部 | Q37: 大区品种线 | Y37: =YEAR(C37) -> 2025 | Z37: =MONTH(C37) -> 12 | AA37: =DAY(C37) -> 15
A38: YMYXMM250569 | B38: 45943 | C38: 46006 | D38: 商务扣款 | E38: 关于潘钟明、余剑玲、黄东宇、林雪清、许忠炯、广东双谷、双胞胎陈粮合同折价的情况说明 | F38: 因无陈粮库存交货，经多次反复沟通协商，以下打包厂、饲料厂陈粮合同剩余未提量在”佳升56/2521“、“锦江河/2519”、“海腾炜业6/2508”、“锦江河/2521”、“利泰朝阳/2524”新船执行，申请在新船执行量折价30元/吨，以下为具体明细 | H38: 品质不达标（容重、水分、毒素、蛋白等） | I38: 4800 | J38: 160 | K38: 佳升56/2521 | L38: YMYXMM250569 | M38: 粤西经营部 | N38: 饲料原料部 | O38: 余诗莹 | P38: 饲料原料部 | Q38: 大区品种线 | Y38: =YEAR(C38) -> 2025 | Z38: =MONTH(C38) -> 12 | AA38: =DAY(C38) -> 15
A39: YMYXMM250564 | B39: 45943 | C39: 46006 | D39: 商务扣款 | E39: 关于潘钟明、余剑玲、黄东宇、林雪清、许忠炯、广东双谷、双胞胎陈粮合同折价的情况说明 | F39: 因无陈粮库存交货，经多次反复沟通协商，以下打包厂、饲料厂陈粮合同剩余未提量在”佳升56/2521“、“锦江河/2519”、“海腾炜业6/2508”、“锦江河/2521”、“利泰朝阳/2524”新船执行，申请在新船执行量折价30元/吨，以下为具体明细 | H39: 品质不达标（容重、水分、毒素、蛋白等） | I39: 12204 | J39: 406.8 | K39: 佳升56/2521 | L39: YMYXMM250564 | M39: 粤西经营部 | N39: 饲料原料部 | O39: 余诗莹 | P39: 饲料原料部 | Q39: 大区品种线 | Y39: =YEAR(C39) -> 2025 | Z39: =MONTH(C39) -> 12 | AA39: =DAY(C39) -> 15
A40: YMYXMM250576 | B40: 45943 | C40: 46006 | D40: 商务扣款 | E40: 关于潘钟明、余剑玲、黄东宇、林雪清、许忠炯、广东双谷、双胞胎陈粮合同折价的情况说明 | F40: 因无陈粮库存交货，经多次反复沟通协商，以下打包厂、饲料厂陈粮合同剩余未提量在”佳升56/2521“、“锦江河/2519”、“海腾炜业6/2508”、“锦江河/2521”、“利泰朝阳/2524”新船执行，申请在新船执行量折价30元/吨，以下为具体明细 | H40: 品质不达标（容重、水分、毒素、蛋白等） | I40: 14578.5 | J40: 485.95 | K40: 锦江河/2519 | L40: YMYXMM250576 | M40: 粤西经营部 | N40: 饲料原料部 | O40: 余诗莹 | P40: 饲料原料部 | Q40: 大区品种线 | Y40: =YEAR(C40) -> 2025 | Z40: =MONTH(C40) -> 12 | AA40: =DAY(C40) -> 15
A41: YMYXMM250507 | B41: 45946 | C41: 46006 | D41: 商务扣款 | E41: 关于潘钟明、余剑玲、黄东宇、林雪清、许忠炯、广东双谷、双胞胎陈粮合同折价的情况说明 | F41: 因无陈粮库存交货，经多次反复沟通协商，以下打包厂、饲料厂陈粮合同剩余未提量在”佳升56/2521“、“锦江河/2519”、“海腾炜业6/2508”、“锦江河/2521”、“利泰朝阳/2524”新船执行，申请在新船执行量折价30元/吨，以下为具体明细 | H41: 品质不达标（容重、水分、毒素、蛋白等） | I41: 24489 | J41: 816.3 | K41: 利泰朝阳/2524 | L41: YMYXMM250507 | M41: 粤西经营部 | N41: 饲料原料部 | O41: 余诗莹 | P41: 饲料原料部 | Q41: 大区品种线 | Y41: =YEAR(C41) -> 2025 | Z41: =MONTH(C41) -> 12 | AA41: =DAY(C41) -> 15
A42: YMLDW251027018 | B42: 45957 | C42: 46001 | D42: 商务扣款 | E42: 关于福建省南平市悠农饲料有限公司商务扣款的申请 | F42: 2025年10月27日我司与福建省南平市悠农饲料有限公司签订《粮食销售合同》(合同编号:YMLDW251027018)，数量1500吨，单价2260元/吨，该票集装箱计划号:YHSZ-25-092308-1、YHSZ-25-092308-2沈阳鑫封缘发至漳州港，合计11个柜，10月31日到港，11月13日提货反馈水分超标，箱内玉米发热，大面积结块，底下一层全部发黑发霉结块，福建经营部销售人员严代亮、沈业润第一时间到厂核实后将情况上报集装箱小组并已在质量反馈表上填报。经过友好协商，客户同意接货做扣款处理，该三组10柜数量为303.82吨，按照单吨扣款100元/吨，合计扣款30382元(附上客户商函及工厂收货现场照片)。 | H42: 质量问题（霉变、霉味、生虫等） | I42: 30382 | J42: 1500 | K42: 集装箱 | L42: YMLDW251027018 | M42: 福建经营部 | N42: 饲料原料部 | O42: 严代亮 | Y42: =YEAR(C42) -> 2025 | Z42: =MONTH(C42) -> 12 | AA42: =DAY(C42) -> 10
A43: JZXYMFJZZ250045 | B43: 45950 | C43: 45988 | D43: 商务扣款 | E43: 关于永安鑫华港饲料有限公司商务扣款的申请 | F43: 2025年10月20日我司与永安鑫华港饲料有限公司签订《粮食销售合同》(合同编号:JZXYMFJZZ250045)，数量685吨，单价2285元/吨，该票集装箱计划号:YHSZ-25-092307沈阳福满仓库发至漳州港，提单号:2G25098728090F，号:ZGXU2534719，该柜10月16日到港，10月27日提货反馈水分超标，发热有异味，经过友好协商，客户同意接货做扣款处理，该柜数量为28.37吨，按照单吨扣款50元/吨，合计扣款1418.5元(附上客户检验报告及扣款函) | H43: 质量问题（霉变、霉味、生虫等） | I43: 97622 | J43: 1952.44 | K43: 集装箱 | L43: YMYXMM250594 | M43: 福建经营部 | N43: 饲料原料部 | O43: 沈业润 | P43: 饲料原料部 | Q43: 大区品种线 | Y43: =YEAR(C43) -> 2025 | Z43: =MONTH(C43) -> 11 | AA43: =DAY(C43) -> 27
A44: YMYXMM250594 | B44: 45961 | C44: 46006 | D44: 商务扣款 | E44: 关于广东域强YMYXMM250594陈粮合同折价的情况说明 | F44: 广东域强粮油贸易有限公司YMYXMM250594，签订日期2025年10月15日，合同量2410元，单价2410元。该合同为陈粮合同，共提货1952.44吨。因无陈粮库存交货，经多次反复沟通协商，分别在”佳升56/2521“新船执行1863.78吨，在”锦江河/2521“新船执行88.66吨，现申请在新船执行量折价50元/吨，折价金额为97622元。 | Y44: =YEAR(C44) -> 2025 | Z44: =MONTH(C44) -> 12 | AA44: =DAY(C44) -> 15
A45: YMFJFZ250174 | B45: 11-14-22 | C45: 46000 | D45: 商务扣款 | E45: 双胞胎（集团）股份有限公司 | F45: 兹有我司与双胞胎（集团）股份有限公司签订《粮食销售合同》（合同号：YMFJFZ250174）合同数量2000吨，单价2335元/吨，合同约定呕吐毒素≤1000ppb。该合同实际执行2007.92吨，在提货过程中,出现部分车次呕吐毒素超标问题,该合同扣款金额为9919.4元,折合扣款4.94元/吨。该批次提货对应军航码头散船弘泰612/2524、华源盛/2529（挑选出货），该批次销售为双胞胎集团下属工厂屏南双胞胎饲料有限公司，为首次开发工厂，客户扣款已在后续合同中以保毒素玉米价格加价给我司（YMFJFZ250188合同，1000吨，2425元/吨，加价16元/吨） | Y45: =YEAR(C45) -> 2025 | Z45: =MONTH(C45) -> 12 | AA45: =DAY(C45) -> 9
A46: YMHN250282 | B46: 45989 | C46: 46000 | D46: 商务扣款 | E46: 河南牧原粮食贸易有限公司扣款说明 | F46: 我司与河南牧原粮食贸易有限公司于2025年11月3日签订的《粮食销售合同》（合同号： YMHN250282），合同数量285吨，合同单价2390元/吨（送到厂价）。截止目前到厂数量500吨，合同单价2330元/吨（送到厂价），合同约定水分≤15%。截止目前到货数量486.28吨，执行完毕。该合同货物在接卸过程中发现一车货物水分15.3%，不符合合同约定标准。此车玉米到厂数量32.32吨，经双方友好协商，此车玉米按5元/吨进行扣价接收，合计扣款¥161.6元。 | H46: 品质不达标（容重、水分、毒素、蛋白等） | I46: 32.32 | J46: 161.6 | K46: 益嘉98/2528 | L46: YMHN250282 | M46: 海南经营部 | N46: 饲料原料部 | O46: 范闻超 | Y46: =YEAR(C46) -> 2025 | Z46: =MONTH(C46) -> 12 | AA46: =DAY(C46) -> 9
A47: YMFJZZ250298 | B47: 46001 | C47: 46007 | D47: 商务扣款 | E47: 有关漳州大北农农牧科技有限公司玉米商务扣款事项 | F47: 我司与漳州大北农农牧科技有限公司于2025年11月19日签订《粮食销售合同（赊销）》（合同编号：YMFJZZ250298），数量1500吨，单价2350元/吨。该合同已累计提1300.32吨，客户于2025年11月月25日至11月26提货的提货玉米合计223.08吨，到货后检测出呕吐毒素超标、杂质的的情况，因我司与客户合同约定指标呕吐毒素指标≤1000ug/kg，杂质≤1.0%，经与工厂、物流等人员确认事实属实，经双方友好协商，该批次货物由退货转扣款接收。以上情况产生扣款5872.50元。 | H47: 品质不达标（容重、水分、毒素、蛋白等） | I47: 9872.5 | J47: 233.08 | K47: 三水809/2525 | L47: YMFJZZ250298 | M47: 福建经营部 | N47: 饲料原料部 | O47: 严代亮 | Y47: =YEAR(C47) -> 2025 | Z47: =MONTH(C47) -> 12 | AA47: =DAY(C47) -> 16
A48: YMFJFZ250114 | B48: 45980 | C48: 46001 | D48: 商务扣款 | E48: 有关正大原料供应有限公司玉米商务扣款事项 | F48: 我司与正大原料供应有限公司于 2025 年8月27日签订《粮食销售合同》（合同编号：YMFJFZ250114 ），数量 500 吨，单价2400元/吨，合同约定杂质≤1%，不完善粒≤8%，呕吐毒素≤1000ug/kg。 客户于9月底前多次检测陈粮玉米利福开拓/2525轮上货物，但玉米毒素超过1500ug/kg，工厂无法使用，原计划交付正大的玉米我司改过筛对圣农集团玉米合同进行交付（交付JZXYMFJFZ250036合同，单价2600元/吨到厂，折算军航码头价格2500元/吨）。 对于正大集团因我司无法按时交付满足质量标准的货物，9月末与10月初市场持续跌价约150元/吨，客户计划取消该合同。后经双方友好协商，我司换新产季玉米于10月底开始交付，客户延期执行上述销售合同，客户预计对该合同换新产季玉米接收预计折价60元/吨，该合同折单价2340元/吨。 客户于2025年11月3日-11月19日提货的477.09吨玉米存在部分毒素超过1000ug/kg，杂质超标、破损较大的问题，存在品质扣款9,951.25元，折单吨20.8元/吨。所提货物匹配船：海百15/2523。 经双方多次沟通，客户对该批次货物进行折价接收，以上情况合计产生扣款38576.65元（大写：人民币叁万捌仟伍佰柒拾陆元陆角伍分）.该合同累计提货477.09吨，折单吨扣80.8元/吨。该合同我司为转新玉米对客户的合同进行交付,对于毒素扣款我司在前期销售时已加30元/吨，可覆盖品质扣款。 以上扣款是否可行，烦请领导批示，谢谢。 | H48: 其他原因 | I48: 38576.65 | J48: 477.09 | K48: 海百15/2523 | L48: YMFJFZ250114 | M48: 福建经营部 | N48: 饲料原料部 | O48: 杜宜衡 | Y48: =YEAR(C48) -> 2025 | Z48: =MONTH(C48) -> 12 | AA48: =DAY(C48) -> 10
A49: YMFJZZ250273 | B49: 45987 | C49: 46001 | D49: 商务扣款 | E49: 有关正大原料供应有限公司玉米商务扣款事项 | F49: 我司与正大原料供应有限公司于 2025 年11月3日签订《粮食销售合同》（合同编号：YMFJZZ250273），数量 500 吨，单价2250元/吨。该合同已累计提505.74吨，客户2025年11月20日-11月26日接收的505.74吨玉米存在杂质超标、破损较大的问题。所提货物匹配船：宁兴18/2525。 经双方友好协商，正大对该批次货物进行折价接收，以上情况合计产生扣款5240.75元（大写：人民币伍仟贰佰肆拾元柒角伍分），该批次累计提货505.74吨，合计折单吨扣款10.36元/吨。该合同销售时已加价10元/吨。 以上扣款是否可行，烦请领导批示，谢谢。 | H49: 品质不达标（容重、水分、毒素、蛋白等） | I49: 5240.75 | J49: 505.74 | K49: 宁兴18/2525 | L49: YMFJFZ250114 | M49: 福建经营部 | N49: 饲料原料部 | O49: 杜宜衡 | Y49: =YEAR(C49) -> 2025 | Z49: =MONTH(C49) -> 12 | AA49: =DAY(C49) -> 10
A50: YMFJZZ250287 | B50: 45984 | C50: 46007 | D50: 商务扣款 | E50: 有关福建湘大骆驼饲料有限公司玉米商务扣款事项 | F50: 我司与福建湘大骆驼饲料有限公司于 2025 年9月22日签订《粮食销售合同》（合同编号：YMFJZZ250287），数量 300 吨，单价2310元/吨。 客户2025年11月22日-11月23日接收的196.3吨玉米客户检测杂质偏大（杂质检测在1.1%-1.8%），部分车辆杂质超标,与客户多次进行协商后，客户扣款2224.53元接收，所提货物匹配船：宁兴18/2525。该合同累计提货295.02吨，折合单吨扣款7.5元/吨。 福建湘大骆驼饲料有限公司对该批次货物进行折价接收，以上情况合计产生扣款2224.53元（大写：人民币贰仟贰佰贰拾肆元伍角叁分）。该合同签订 以上扣款是否可行，烦请领导批示，谢谢。 | H50: 品质不达标（容重、水分、毒素、蛋白等） | I50: 2224.53 | J50: 196.3 | K50: 宁兴18/2525 | L50: YMFJZZ250287 | M50: 福建经营部 | N50: 饲料原料部 | O50: 杜宜衡 | Y50: =YEAR(C50) -> 2025 | Z50: =MONTH(C50) -> 12 | AA50: =DAY(C50) -> 16
A51: JZXYMFJFZ250080 | B51: 45960 | C51: 45994 | D51: 商务扣款 | E51: 有关三明市丰源饲料有限公司玉米商务扣款事项 | F51: 我司与三明市丰源饲料有限公司于 2025 年10月22日签订《粮食销售合同》（合同编号：JZXYMFJFZ250080），数量 500 吨，单价2260元/吨。该合同已累计提货490.35吨，客户2025年10月25日-10月30日接收的102.52吨集装箱货物，因新玉米水分不稳定，到货存在发热情况，扣款60元/吨。 经双方友好协商，三明市丰源饲料有限公司对该批次货物进行折价接收，以上情况合计产生扣款6151.2元（大写：人民币陆仟壹佰伍拾壹元贰角），该批次累计提货490.35吨，合计折单吨扣款12.55元/吨。 以上扣款是否可行，烦请领导批示，谢谢。 | H51: 品质不达标（容重、水分、毒素、蛋白等） | I51: 6151.2 | J51: 102.52 | K51: CSNU2898120 CSNU2889900 CSNU2906530 CSNU2821983 CSNU2806994 | L51: JZXYMFJFZ250080 | M51: 福建经营部 | N51: 饲料原料部 | O51: 杜宜衡 | Y51: =YEAR(C51) -> 2025 | Z51: =MONTH(C51) -> 12 | AA51: =DAY(C51) -> 3
A52: JZXYMFJFZ250074 | B52: 45952 | C52: 45952 | D52: 商务扣款 | E52: 有关福建省金同星汇贸易有限公司玉米商务扣款事项 | F52: 我司与福建省金同星汇贸易有限公司于 2025 年10月12日签订《粮食销售合同》（合同编号：JZXYMFJFZ250074），数量210吨，单价2345元/吨。该合同已累计提货209.155吨，客户2025年10月22日接收的集装箱CSNU2904028、CSNU2895414，因新玉米水分不稳定，到货存在发热情况，客户扣款接收。所提集装箱计划号：YHSZ-25-092310，禹泰库。该批集装箱10月18日到货。 经双方友好协商，福建省金同星汇贸易有限公司对该批次货物进行折价接收，以上情况合计产生扣款2,030.00 元（大写：人民币贰仟零叁拾），该批次累计提货209.155吨，合计折单吨扣款10元/吨。我司与客户签订该合同时间，已对比同期指导价格加价40元/吨进行销售，同时对后续批次交货进行挑选后出货，可覆盖扣款。 | H52: 品质不达标（容重、水分、毒素、蛋白等） | I52: 2030 | J52: 209.155 | K52: CSNU2904028、CSNU2895414 | L52: JZXYMFJFZ250074 | M52: 福建经营部 | N52: 饲料原料部 | O52: 杜宜衡 | Y52: =YEAR(C52) -> 2025 | Z52: =MONTH(C52) -> 10 | AA52: =DAY(C52) -> 22
A53: YMZSJQY250105 | B53: 45916 | C53: 45916 | D53: 商务扣款 | E53: 关于安徽正康饲料有限责任公司扣款的说明 | F53: 我司与安徽正康饲料有限责任公司于 2025 年6月26 日签订的《粮食销售合同》合同号 YMZSJQY250105，单价 2555 元/吨，数量 2000 吨，客户提货我司库存前移驳船:粤海 36 轮货物(该船清仓我司弘泰 819 货物1069.982吨+京粮/250115合同货物 209.72吨，装货时已出现粉尘较大、霉变现象，后续出现发热情况)，共计库存前移 1279.702吨，客户于8月 26 日开始提货到厂 299.94 吨,反馈提货时出现大量粉尘。于 2025年8月31 日开始到货共计 299.86 吨，到厂后发现该船玉米有出现大量的粉尘杂质，玉米都被淹没在粉尘杂质里，碎粒、粉尘占比达5.75%，同时经过测验:呕吐毒素测试分别为1231.04，1837.26，不符合客户合同签订指标中质量验收标准，我司销售人员9月去现场查看后，确认情况属实，后经过销售与客户沟通,又于9月 16 日协助我司提货 99.82 吨共计三车货物。粤海 36 轮剩余货物 350.92吨由于质量较差无法使用，为避免货物质量进一步受损，销售给韶关市源饲料有限公司(价格:2270 元/吨)，经过销售与客户沟通，客户原计划扣款100元/吨，现经过双方友好协商，客户共计提货699.62吨，申请对8月26日开始提货到厂的299.94吨扣款 40元/吨，对8月31 日和9月 16 日提货的玉米共计 399.68 吨，进行扣款 70 元/吨，共计扣款 299.94*40+399.68*70=39975.2元。请领导批示 | H53: 质量问题（霉变、霉味、生虫等） | I53: 39975.2 | J53: 699.62 | K53: 弘泰819 | L53: YMZSJQY250105 | M53: 珠三角经营部 | Y53: =YEAR(C53) -> 2025 | Z53: =MONTH(C53) -> 9 | AA53: =DAY(C53) -> 16
A54: YMZSJDGJZX250422 | B54: 46000 | C54: 46009 | D54: 商务扣款 | E54: 关于YMZSJDGJZX250422合同扣款说明 | F54: 我司与 中山市福大生物科技有限公司 于2025年 11月28日签署的粮食销售合同：YMZSJDGJZX250422（合同量：382吨，单价：2420元/吨）；客户提货到厂检测出现6个柜子出现容重低、毒素超标、水分超标情况（运单号：JZ21JZLX1454F7），对于该6个柜子扣款15元/吨处理，合计162.66吨*15元/吨=2439.9元； | H54: 品质不达标（容重、水分、毒素、蛋白等） | I54: 2439.9 | J54: 162.66 | K54: JZ21JZLX1454F7 | L54: YMZSJDGJZX250422 | M54: YMZSJDGJZX250422 | Y54: =YEAR(C54) -> 2025 | Z54: =MONTH(C54) -> 12 | AA54: =DAY(C54) -> 18
A55: YMZSJDKHLY250180 | B55: 45991 | C55: 46010 | D55: 商务扣款 | E55: 关于贵州漓源饲料有限公司YMZSJDKHLY250180扣款的请示 | F55: 我司于2025年11月6日与贵州漓源饲料有限公司签订内贸玉米合同，编号YMZSJDKHLY250180，数量1000吨，单价2240元/吨。 客户于南沙港东星海泰/077灌箱提货，提单号NSDXHT7725009，因工厂检测杂质偏高，综合平均杂质约2.99%。因对客户成品以及口碑造成影响，扣价15元/吨，需扣价:997.544*15=14963.16元。 | H55: 质量问题（霉变、霉味、生虫等） | I55: 14963.16 | J55: 997.544 | K55: 东星海泰/077 | L55: YMZSJDKHLY250180 | M55: 珠三角经营部 | N55: 饲料原料部 | O55: 李长聪 | Y55: =YEAR(C55) -> 2025 | Z55: =MONTH(C55) -> 12 | AA55: =DAY(C55) -> 19
A56: YMZSJDKHWS250037 | B56: 46001 | C56: 46010 | D56: 商务扣款 | E56: 温氏集团扣款情况说明 | F56: 2025年11月24日 我司与 信丰温氏畜牧有限公司 签订内贸玉米合同，协议号：YMZSJDKHWS250037，数量1500吨，单价2360元/吨。客户提麻涌港 东星海泰/078货物，报161.76吨货物赤霉烯酮（250ppb）超标，单吨扣价10元，合计扣款1617.6元。 | H56: 质量问题（霉变、霉味、生虫等） | I56: 1617.6 | J56: 161.76 | K56: 东星海泰/078 | L56: YMZSJDKHWS250037 | M56: 珠三角经营部 | N56: 饲料原料部 | O56: 凌梓峰 | Y56: =YEAR(C56) -> 2025 | Z56: =MONTH(C56) -> 12 | AA56: =DAY(C56) -> 19
A57: YMZSJDKHWS250025-3 | B57: 46001 | C57: 46010 | D57: 商务扣款 | E57: 温氏集团扣款情况说明 | F57: 2025年11月13日我司与 富川广东温氏畜牧有限公司 签订内贸玉米转让协议，合同号：YMZSJDKHWS250025-3 ，数量1000 吨，单价2290元/吨。客户提麻涌港 东星海泰/078，报189.68吨货物赤霉烯酮( 290 ppb)超标，属于折价接收范围，单吨扣价10元，合计扣款1896.8元。 | H57: 质量问题（霉变、霉味、生虫等） | I57: 1896.8 | J57: 189.68 | K57: 东星海泰/078 | L57: YMZSJDKHWS250025-3 | M57: 珠三角经营部 | N57: 饲料原料部 | O57: 凌梓峰 | Y57: =YEAR(C57) -> 2025 | Z57: =MONTH(C57) -> 12 | AA57: =DAY(C57) -> 19
A58: YMZSJDKHWS250025-2 | B58: 46001 | C58: 46010 | D58: 商务扣款 | E58: 温氏集团扣款情况说明 | F58: 2025年11月12日我司与 河源市温氏禽畜有限公司 签订内贸玉米转让协议，协议号：YMZSJDKHWS250025-2，数量1000吨，单价2290元/吨。客户提麻涌港 东星海泰/078货物，报29.2吨货物杂质（ 3.34 ）超标，属于折价接收范围，单吨扣价10元，合计扣款292元。 | H58: 品质不达标（容重、水分、毒素、蛋白等） | I58: 292 | J58: 29.2 | K58: 东星海泰/078 | L58: YMZSJDKHWS250025-2 | M58: 珠三角经营部 | N58: 饲料原料部 | O58: 凌梓峰 | Y58: =YEAR(C58) -> 2025 | Z58: =MONTH(C58) -> 12 | AA58: =DAY(C58) -> 19
A59: YMZSJDKHWS250030 | B59: 46001 | C59: 46010 | D59: 商务扣款 | E59: 温氏集团扣款情况说明 | F59: 2025年11月13日 我司与 道县温氏畜牧有限公司 签订内贸玉米合同，合同号：YMZSJDKHWS250030 ，数量2500吨，单价2305元/吨。客户提麻涌港 国家能源610/2511货物，报1154.2吨货物 杂质（2.07-13.07）超标，属于折价接收范围，单吨扣价10元，合计扣款11542元。 | H59: 品质不达标（容重、水分、毒素、蛋白等） | I59: 11542 | J59: 1154.2 | K59: 国家能源610/2511 | L59: YMZSJDKHWS250030 | M59: 珠三角经营部 | N59: 饲料原料部 | O59: 凌梓峰 | Y59: =YEAR(C59) -> 2025 | Z59: =MONTH(C59) -> 12 | AA59: =DAY(C59) -> 19
A60: YMZSJDKHWS250033 | B60: 46001 | C60: 46010 | D60: 商务扣款 | E60: 温氏集团扣款情况说明 | F60: 2025年11月17日我司与 大余温氏畜牧有限公司 签订内贸玉米合同，协议号：YMZSJDKHWS250033，数量1000吨，单价2350元/吨。客户提麻涌港 国家能源610/2511货物，报549.32吨货物杂质（1.32%-1.67%）、呕吐毒素（2250-2440）和赤霉烯酮( 1734 ppb)超标，属于折价接收范围，单吨扣价15元，合计扣款8239.8元。 | H60: 质量问题（霉变、霉味、生虫等） | I60: 8239.8 | J60: 549.32 | K60: 国家能源610/2511 | L60: YMZSJDKHWS250033 | M60: 珠三角经营部 | N60: 饲料原料部 | O60: 凌梓峰 | Y60: =YEAR(C60) -> 2025 | Z60: =MONTH(C60) -> 12 | AA60: =DAY(C60) -> 19
A61: YMYXMM250391 | B61: 45920 | C61: 46010 | D61: 商务扣款 | E61: 关于茂名响亮 YMYXMM250391 质量扣款的情况说明 | F61: 茂名响亮饲料有限公司 YMYXMM250391（合同量 3000 吨，单价 2406 元），合同约定呕吐毒素≤ 1000ug/kg。该合同执行 3005.77 吨，在中心不保毒大船“鑫海城 1/2516”轮提货过程中，252.01 吨存在 毒素超标的质量问题，在 1025-1574ppb 之间，不符合同规定。经我司业务人员核实，检测结果确实存在。 秉承长期友好合同原则，经我部与客户多次友好协商后，做扣价 30 元/吨处理，申请扣款金额合计 7560.3 元。该扣款情况已报备饲料原料部。已在 YMYXMM250391 合同成交时预留 30 元/吨溢价处理质量扣款， 预留价差可覆盖扣款。由于该合同已经结算完毕，申请在 JZXYMYXMM250507 合同抵扣扣款 | H61: 品质不达标（容重、水分、毒素、蛋白等） | I61: 7560.3 | J61: 252.01 | K61: 鑫海城 1/2516 | L61: YMYXMM250391 | M61: 粤西经营部 | N61: 饲料原料部 | O61: 余诗莹 | Y61: =YEAR(C61) -> 2025 | Z61: =MONTH(C61) -> 12 | AA61: =DAY(C61) -> 19
A62: YMYXMM250392 | B62: 45941 | C62: 46010 | D62: 商务扣款 | E62: 关于茂名金源 YMYXMM250392 质量扣款的情况说明 | F62: 茂名金源生物科技有限公司 YMYXMM250392（合同量 2000 吨，单价 2409 元），合同约定呕吐毒素 ≤1000ug/kg。该合同执行 1972.24 吨，安排在中心大船“鑫海城 1/2516、远泰 99/2521”轮提货不保毒 素玉米，1754.02 吨存在毒素超标的质量问题，在 1012-1350ppb 之间，不符合同规定。经我司业务人员核 实，检测结果确实存在。秉承长期友好合同原则，经我部与客户多次友好协商后，做扣价 20 元/吨处理，申 请扣款金额合计 35080.4 元。该扣款情况已报备饲料原料部。已在 YMYXMM250392 合同成交时预留 20 元/吨溢价处理质量扣款，预留价差可覆盖扣款。由于该合同已经结算完毕，申请在 YMYXMM250778 合同 抵扣。 | H62: 品质不达标（容重、水分、毒素、蛋白等） | I62: 35080.4 | J62: 1754.02 | K62: 鑫海城 1/2516、远泰 99/2521 | L62: YMYXMM250392 | M62: 粤西经营部 | N62: 饲料原料部 | O62: 余诗莹 | Y62: =YEAR(C62) -> 2025 | Z62: =MONTH(C62) -> 12 | AA62: =DAY(C62) -> 19
A63: YMZSJJM25081 | B63: 45997 | C63: 46013 | D63: 商务扣款 | E63: 关于YMZSJJM25081玉米杂质超标扣款费 | F63: 江门市旺海饲料实业有限公司，于2025 年 11 月24 日签订的《粮食销售合同（赊销）》合同编号:YMZSJJM25081)合同数量2000吨,合同单价2373元/吨，配送船只粤新会货 8093存在玉米杂质超标扣款费用： 船号粤新会货8093，卸船重量995.958吨，该批玉米验收过程时检测出杂质为3.34%,超出合同标准1.34%,江门市旺海饲料实业有限公司提出该船折价20元/吨让步接收处理，总计费用：995.958*20=19919.16元。 | H63: 品质不达标（容重、水分、毒素、蛋白等） | I63: 19919.16 | J63: 995.958 | K63: 东星海泰/076、东星海泰/078 | L63: YMZSJJM25081 | M63: 珠三角经营部 | N63: 饲料原料部 | O63: 汤妮 | P63: 珠三角经营部 | Q63: 大区品种线 | Y63: =YEAR(C63) -> 2025 | Z63: =MONTH(C63) -> 12 | AA63: =DAY(C63) -> 22
A64: JZXYMFJFZ250075 | B64: 45989 | C64: 46013 | D64: 商务扣款 | E64: 有关三明海大饲料有限公司玉米商务扣款事项 | F64: 我司与三明海大饲料有限公司于 2025 年10月20日签订《粮食销售合同》（合同编号：JZXYMFJFZ250075），数量500吨，单价2360元/吨。该合同已累计提498.07吨，客户2025年11月1日-2025年11月28日接收的167.16吨玉米存在水分超标发热、毒素超标等情况。所提货物匹配计划号：YHSZ-25-092324，宏泰源库；YHSZ-25-092311，禹泰库。 经双方友好协商，三明海大饲料有限公司对该批次货物进行折价接收，以上情况合计产生扣款5133.43元（大写：人民币伍仟壹佰叁拾叁元肆角叁分），该批次累计提货498.07吨，折单吨扣款10.3元/吨，因合同签订保呕吐毒素，前期已加价15元/吨进行销售，可涵盖扣款损失. | H64: 品质不达标（容重、水分、毒素、蛋白等） | I64: 5133.43 | J64: 167.16 | K64: YHSZ-25-092324，宏泰源库；YHSZ-25-092311，禹泰库 | L64: JZXYMFJFZ250075 | M64: 福建经营部 | N64: 饲料原料部 | O64: 杜宜衡 | Y64: =YEAR(C64) -> 2025 | Z64: =MONTH(C64) -> 12 | AA64: =DAY(C64) -> 22
A65: JZXYMFJFZ250072 | B65: 45957 | C65: 46013 | D65: 商务扣款 | E65: 有关营口长源物流供应链管理有限公司玉米商务扣款事项 | F65: 我司与营口长源物流供应链管理有限公司于 2025 年10月13日签订《粮食销售合同》（合同编号：JZXYMFJFZ250072），数量 540吨，单价2300元/吨。合同约定杂质≤1%，不完善粒≤8%，呕吐毒素≤1000ug/kg。 客户于10月27日提货的集装箱经过水分检测均存在超15%的情况，部分集装箱有轻微发热的情况，根据检测结果，客户的对水分检测超15.5%的6柜集装箱，每吨扣款30元/吨接收，合计产生扣款4898.7元，折单吨扣款9元/吨。该批集装箱匹配计划号：YHSZ-25-092310，禹泰库。我司前期已对该批集装箱水分超标情况登记反馈。 因考虑到该客户为终端销售，该批次销售猪料客户，因此在销售时，已加价20元/吨进行销售，溢价可涵盖上述扣款损失。 以上扣款是否可行，烦请领导批示，谢谢。 | H65: 品质不达标（容重、水分、毒素、蛋白等） | I65: 4898.7 | J65: 164.39 | K65: YHSZ-25-092310，禹泰库 | L65: JZXYMFJFZ250072 | M65: 福建经营部 | N65: 饲料原料部 | O65: 杜宜衡 | Y65: =YEAR(C65) -> 2025 | Z65: =MONTH(C65) -> 12 | AA65: =DAY(C65) -> 22
A66: JCYMZSJDG25053-1 | B66: 45981 | C66: 46014 | D66: 商务扣款 | E66: 关于播恩集团股份有限公司 JCYMZSJDG25053-1 扣款的请示 | F66: 客户于麻涌港东耀海泰提货，有一车（车号皖LD5749）32.40 吨玉米检测毒素不符合合同标准 | H66: 品质不达标（容重、水分、毒素、蛋白等） | I66: 324 | J66: 32.4 | K66: 东耀海泰066 | L66: JCYMZSJDG25053-1 | M66: 珠三角经营部 | N66: 饲料原料部 | O66: 林佳琦 | Y66: =YEAR(C66) -> 2025 | Z66: =MONTH(C66) -> 12 | AA66: =DAY(C66) -> 23
A67: YMFJFZ250086 | B67: 2025-8-14-9-14 | C67: 46014 | D67: 商务扣款 | E67: 有关福建省邵武市华龙饲料有限公司玉米商务扣款事项 | F67: 我司与福建省邵武市华龙饲料有限公司于 2025 年7月14日签订《粮食销售合同》（合同编号：YMFJFZ250086），数量3000吨，单价2410元/吨。该合同累计提货3119.12吨，客户2025年8月14日-2025年9月13日接收的1084.11吨玉米，出现杂质及霉变超标情况，客户原诉求扣款51398.46元，经双方多次沟通后，客户同意扣款21584.2元（附客户扣款商函及照片），折合6.92元/吨。 以上扣款，对应船舶昌晟隆/2523、明金2号/2523，是否可行，烦请领导批示，谢谢。 | H67: 质量问题（霉变、霉味、生虫等） | I67: 21584.2 | J67: 3119.12 | K67: 昌晟隆/2523、明金2号/2523 | L67: YMFJFZ250086 | M67: 福建经营部 | N67: 饲料原料部 | O67: 许开兴 | Y67: =YEAR(C67) -> 2025 | Z67: =MONTH(C67) -> 12 | AA67: =DAY(C67) -> 23
A68: YMFJFZ250187 | B68: 11-24-29 | C68: 46014 | D68: 商务扣款 | E68: 福清双胞胎饲料有限公司 | F68: 我司与福清双胞胎饲料有限公司于 2025 年11月18日签订《粮食销售合同》（合同编号：YMFJFZ250187），数量2000吨，单价2360元/吨。该合同已累计送货1918.48吨，累计接货1914.95吨，客户2025年11月24日-2025年11月29日接收的773.74吨玉米呕吐毒素超标，总计扣款20202.80元，折合10.55元/吨。对应船舶华源盛/2529。该客户原玉米，基本为北方自发到长乐，我部为推动福清双胞胎往军航码头提货，同时推动军航码头电车配送福清双胞胎业务。该单合作是近3年来内贸 玉米的首单合作，主要为双方再此合作磨合（品质、配送等），在销售时未加价销售。接货过程中，我司玉米出现了较大批次的呕吐毒素超标情况，工厂主要生产猪料，对品质要求较为严格，经双方多次友好协商，工厂进行扣款接货，该工厂后续合作，我部将充分考虑实际品质及工厂可能扣款情况，进行溢价销售，涵盖质量损失。 以上扣款是否可行，烦请领导批示，谢谢。 | H68: 品质不达标（容重、水分、毒素、蛋白等） | I68: 20202.8 | J68: 1914.88 | K68: 华源盛/2529 | L68: YMFJFZ250187 | M68: 福建经营部 | N68: 饲料原料部 | O68: 许开兴 | Y68: =YEAR(C68) -> 2025 | Z68: =MONTH(C68) -> 12 | AA68: =DAY(C68) -> 23
B69: 46009 | C69: 46015 | D69: 商务扣款 | E69: 丰顺县海新饲料有限公司 | F69: 于2025年11月28日签订《粮食销售合同》(合同编号:YMZSJJY250186)，数量500吨，单价2410元/吨，该合同己累计交货499.49吨，(其中12月11日4车车号:C1715D，重量34.86吨车号:粤BGT302，重量35.49吨，车号:粤BFS784，重量35.87吨，车号:粤MA1287，重量39.53吨合计:145.75吨)到货玉米经检验杂质1.2%杂质和破碎粒超出合同约定指标(杂质≤1%),不符合客户接受指标针对该批次到厂不合格玉米，经双方友好协商处理后，退货转扣款接收 | H69: 杂质1.2%杂质和破碎粒超出合同约定指标 | I69: 1457.5 | J69: 145.75 | K69: 鑫顺弘盛/2537 | L69: YMZSJJY250186 | M69: 珠三角经营部 | N69: 饲料原料部 | O69: 蚁毓霖 | Y69: =YEAR(C69) -> 2025 | Z69: =MONTH(C69) -> 12 | AA69: =DAY(C69) -> 24
A70: JCYMHN250088-1 | B70: 11-30-12-8 | C70: 46015 | D70: 商务扣款 | E70: 海南省粮油产业有限公司 | F70: 我司与海南省粮油产业有限公司于2025年11月3日签订的《粮食销售合同》（合同号：JCYMHN250088-1），合同数量1500吨，合同单价2257元/吨，截止目前共计执行1487.7吨，执行完毕。该批货物在接卸过程中客户反水分及不完善粒超标等质量问题，我司现场人员范闻超和工厂品管人员共同抽样检测，检测结果事实存在，现场检测水分15.1-15.3%，不完善粒11.7-11.8%不等，合计数量1487.7吨。经双方友好协商，此批玉米按20元/吨进行扣价接收，合计扣款¥29754元。以上扣款具体执行航次为：2025年11月30日抵达马村港“益嘉9/2528”玉米轮执行430.12吨，8602.4元；2025年12月8日抵达马村港“炜业福星/2525”玉米轮执行1057.58吨，扣款21151.6元。 | H70: 品质不达标（容重、水分、毒素、蛋白等） | I70: 29754 | J70: 1487.7 | K70: 益嘉9/2528、炜业福星/2525 | L70: JCYMHN250088-1 | M70: 海南经营部 | N70: 饲料原料部 | O70: 范闻超 | Y70: =YEAR(C70) -> 2025 | Z70: =MONTH(C70) -> 12 | AA70: =DAY(C70) -> 24
A71: JZXYMFJFZ250081 | B71: 11月27日-11月30日 | C71: 46016 | D71: 商务扣款 | E71: 三明海大饲料有限公司 | F71: 我司与三明海大饲料有限公司于 2025 年11月5日签订《粮食销售合同》（合同编号：JZXYMFJFZ250081），数量800吨，单价2330元/吨。该合同已累计提货788.73吨，客户2025年11月27日-2025年11月30日接收的100.74吨玉米存在毒素超标等情况。所提货物匹配计划号：YHSZ-25-092324，宏泰源库、新誉库。 明细如下：到厂日期 车号 重量/吨 备注 2025/11/27 TLLU3079330 10.14 1500ppb 2025/11/27 ZGXU3005031 27.28 1170ppb 2025/11/28 ZGLU3210656 27.34 1110ppb 2025/11/28 ZGXU3032042 8.45 1710ppb 2025/11/30 ZGLU3138757 27.53 1120ppb 经双方友好协商，三明海大饲料有限公司对该批次货物进行折价接收，以上情况合计产生扣款1971.90元（大写：人民币壹仟玖佰柒拾壹元玖角），该批次累计提货788.73吨，折单吨扣款2.5元/吨，合同签订保呕吐毒素，前期已加价15元/吨进行销售，可涵盖扣款损失. 以上扣款是否可行，烦请领导批示，谢谢。 | H71: 品质不达标（容重、水分、毒素、蛋白等） | I71: 1971.9 | J71: 100.74 | K71: YHSZ-25-092324，宏泰源库、新誉库 | L71: YMFJFZ250187 | M71: 福建经营部 | N71: 饲料原料部 | O71: 杜宜衡 | Y71: =YEAR(C71) -> 2025 | Z71: =MONTH(C71) -> 12 | AA71: =DAY(C71) -> 25
A72: JCYMZSJQY250029-2 | B72: 45990 | C72: 46020 | D72: 商务扣款 | E72: 关于安佑集团结算扣价 | F72: 苏州穗满德国际贸易有限公司，2025年11月19日签订的《粮食销售合同》(合同编号:JCYMZSJQY250029-2)合同数量2000吨，合同单价2297.5元/吨，提货麻涌港东星海泰/078，二车到厂检测杂质分别为1.71%、2.98%出合同约定的标准，合计64.92吨，申请分别扣款538与1472元，合计扣款2010元 | H72: 品质不达标（容重、水分、毒素、蛋白等） | I72: 2010 | J72: 64.92 | K72: 东星海泰/078 | L72: JCYMZSJQY250029-2 | M72: 珠三角经营部 | N72: 饲料原料部 | O72: 董典昊 | Y72: =YEAR(C72) -> 2025 | Z72: =MONTH(C72) -> 12 | AA72: =DAY(C72) -> 29
A73: YMZSJDKHLY250195 | B73: 46005 | C73: 46017 | D73: 商务扣款 | E73: 关于韶关市漓源饲料有限公司 YMZSJDKHLY250195 扣款的请示 | F73: 我司于 2025 年 11 月 26 日与韶关市漓源饲料有限公司签订内贸玉米合 同，编号 YMZSJDKHLY250195，数量 1000 吨，单价 2400 元/吨。 客户于麻涌港东星海泰/079 提货，提单号 MCDXHT07925039，因工厂到 厂抽样检测发现 200.04 吨玉米杂质检测均值在 1.82%，达不到合同指标 ≤1% 。 因 对 客 户 成 品 以 及 口 碑 造 成 影 响 ， 扣 价 10 元 / 吨 ， 需 扣 价:200.04*10=2000.4 元。 | H73: 品质不达标（容重、水分、毒素、蛋白等） | I73: 2000.4 | J73: 200.04 | K73: 东星海泰/079 | L73: YMZSJDKHLY250195 | M73: 珠三角经营部 | N73: 饲料原料部 | O73: 李长聪 | Y73: =YEAR(C73) -> 2025 | Z73: =MONTH(C73) -> 12 | AA73: =DAY(C73) -> 26
A74: JZXYMZSJQY250113 | B74: 45997 | C74: 46034 | D74: 商务扣款 | E74: 关于双胞胎JZXYMZSJQY250113结算扣款 | F74: 双胞胎（集团）股份有限公司，2025年12月2日签订的《粮食销售合同》(合同编号:JZXYMZSJQY250113)合同数量400吨,合同单价 2470 元/吨,客户提货外采合同号JZXYMSZCG250092，运单号JZ21JZLX1454A，柜号FTAU1999604，到厂检测结果水分15.38，呕吐毒素1161，超出合同约定的标准，申请扣款35元/吨，26.93吨*35=942.55元。 | H74: 品质不达标（容重、水分、毒素、蛋白等） | I74: 942.55 | J74: 26.93 | K74: JZXYMSZCG250092 | L74: JZXYMZSJQY250113 | M74: 珠三角经营部 | N74: 饲料原料部 | O74: 董典昊 | X74: 水分 | Y74: =YEAR(C74) -> 2026 | Z74: =MONTH(C74) -> 1 | AA74: =DAY(C74) -> 12
A75: JZXYMHN250170 | B75: 45990 | C75: 46020 | D75: 商务扣款 | E75: 海南胜飞贸易有限公司商务扣款说明 | F75: 我司与海南胜飞贸易有限公司于2025年11月21日签订的《粮食销售合同》（合同号：JZXYMHN250170），合同数量550吨，合同单价2400元/吨，质量标准：容重≥700g/L，水分≤15%，杂质≤1.0%，霉变粒≤2.0%，不完善粒≤8%，呕吐毒素≤1000ug/kg。截止目前共计执行547.55吨，执行完毕。该批货物在接卸过程中发现箱号为CSNU3002368发运重量27.11吨，呕吐毒素1480.15ug/kg，不符合合同约定质量标准。经双方友好协商，此批玉米收货重量共计27.21吨，按30元/吨进行扣价接收，合计扣款¥816.3元。 以上扣款货物为对应发运计划编号YHSZ-25-102202，对应装箱库点：营口雨荷库 | H75: 品质不达标（容重、水分、毒素、蛋白等） | I75: 816.3 | J75: 27.21 | K75: 发运计划编号YHSZ-25-102202，对应装箱库点：营口雨荷库 箱号为CSNU3002368发运重量27.11吨 | L75: JZXYMHN250170 | M75: 海南经营部 | N75: 饲料原料部 | O75: 范闻超 | Y75: =YEAR(C75) -> 2025 | Z75: =MONTH(C75) -> 12 | AA75: =DAY(C75) -> 29
A76: JZXYMYXMM250805 | B76: 45994 | C76: 46021 | D76: 商务扣款 | E76: 关于客户潘钟明结算数量的说明 | F76: 2025年11月17日签订的的集装箱合同，潘钟明，合同号JZXYMYXMM250805（322吨，2370元每吨）； 客户在提货中发现提单号ASMWGSU250802497A，箱号：HJLU1340302；北方磅装货一组总数56.32吨。 该箱在码头转运过程中爆箱撒漏，12月3日到货后确认柜体侧面漏洞，撒漏，保险第三方已经处理，经双方协商，本合同扣款金额为4.26吨*2370元/吨=10096.2元。 | H76: 包装破损、水湿、短重等 | I76: 10096.2 | J76: 4.26 | K76: ASMWGSU250802497A | L76: JZXYMYXMM250805 | M76: 粤西经营部 | N76: 饲料原料部 | O76: 许满 | Y76: =YEAR(C76) -> 2025 | Z76: =MONTH(C76) -> 12 | AA76: =DAY(C76) -> 30
A77: JCYMZSJQY250011-1 | B77: 46010 | C77: 46027 | D77: 商务扣款 | E77: JCYMZSJQY250011-1联系单 | F77: 司与成都德康动物健康技术服务有限公司于2025年12月10日签订的<<粮食销售合同>>(赊销),合同号JCYMZSJQY250011-1,单价2361元/吨,数量2000吨。客户于2025年12月16日开单我司麻涌港大船:国家能源/2512轮货物共计1000吨，实际装货:996.818吨，提货驳船粤鼎湖货0388于12月19日到厂后发现有杂质超标情况，经检测杂质达3.43%，合同第二条:质量标准中约定:杂质2%，考虑到杂质检测方法尚存争议，且考虑到双方长期以来的友好合作关系，经双方友好协商，申请对12月19日开始提货到厂的996.818货物扣款23556.96元(折合单吨扣款四舍五入后为23.63元)。 | H77: 品质不达标（容重、水分、毒素、蛋白等） | I77: 23556.96 | J77: 996.818 | K77: 国家能源/2512 | L77: JCYMZSJQY250011-1 | M77: 珠三角经营部 | N77: 饲料原料部 | O77: 郭良伟 | X77: 水分 | Y77: =YEAR(C77) -> 2026 | Z77: =MONTH(C77) -> 1 | AA77: =DAY(C77) -> 5
B78: 46008 | C78: 46029 | D78: 商务扣款 | E78: 关于正大原料供应有限公司内贸玉米业务商务的说明 | F78: 提货杂质大，7车做 25 元/吨扣款，数量 311.46 吨，金额为 7786.5 元。 | H78: 品质不达标（容重、水分、毒素、蛋白等） | I78: 7786.5 | J78: 311.46 | K78: 国家能源610/2512 | L78: YMYMGXXJ250141 | M78: 广西经营部 | N78: 饲料原料部 | O78: 李戈 | X78: 水分 | Y78: =YEAR(C78) -> 2026 | Z78: =MONTH(C78) -> 1 | AA78: =DAY(C78) -> 7
A79: JZXYMLCYDG251207 | B79: 46020 | C79: 46030 | D79: 商务扣款 | E79: 关于合同号JZXYMLCYDG251207扣款说明 | F79: 联系单号:YHSZ-25-111427、YHSZ-25-111429销售广州顺泽粮食贸易有限公司，2025年12月5日签订的《粮食销售合同》(合同编号:JZXYMLCYDG251207)合同数量2500 吨，合同单价 2482元/吨。该合同交货过程中2柜因水湿粘底,杂质破碎杂质大,扣款 20-30 元/吨让步接收,车上粘住卸不下来的 0.36吨客户拒收退回码头仓库 600元/吨让步接收，合计扣款2011.22元 | H79: 质量问题（霉变、霉味、生虫等） | I79: 2011.22 | J79: 53.85 | K79: Q088864200,Q088894811 | L79: JZXYMLCYDG251207 | M79: 珠三角经营部 | N79: 饲料原料部 | O79: 林佳琦 | X79: 霉变 | Y79: =YEAR(C79) -> 2026 | Z79: =MONTH(C79) -> 1 | AA79: =DAY(C79) -> 8
B80: 46024 | C80: 46031 | D80: 商务扣款 | E80: 茂名正辉--关于“炜业68V2507“轮玉米质量扣款情况说明 | F80: 关于茂名正辉有限公司与我司签订了原料采购合同(合同编号:YMYXMM250863)，合同数量500吨，合同约定质量标准：容重≥690g/L，水分≤15%，杂质≤1%，霉变粒≤2%，不完善粒≤10%。客户共有两个合同共1000吨在该条船上提货。客户于1月2日在茂名市长晟码头世恒2仓“炜业68V2507“轮提货3车(98.85吨)发现玉米杂质达到4%，呕吐毒素达到2150ug/kg,客户为生产猪料工厂，杂质及呕吐毒素超标只能降级使用，经友好商务沟通，客户同意折价接收，现申请如下： 3车申请扣款20元/吨，共98.85吨，共计扣款1979元 | H80: 品质不达标（容重、水分、毒素、蛋白等） | I80: 1979 | J80: 98.85 | K80: 炜业68V2507 | L80: YMYXMM250863 | M80: 粤西经营部 | N80: 饲料原料部 | O80: 许满 | X80: 水分 | Y80: =YEAR(C80) -> 2026 | Z80: =MONTH(C80) -> 1 | AA80: =DAY(C80) -> 9
A81: JZXYMZSJJM25040 | B81: 46016 | C81: 46016 | D81: 商务扣款 | E81: 广州顺泽粮食贸易有限公司 | F81: 广 州 顺 泽 粮 食 贸 易 有 限 公 司 ， 2025 年 9 月 8 日 签 订 的 《 粮 食 销 售 合 同 》 ( 合 同 编 号:JZXYMZSJJM25040)合同数量 540 吨，合同单价 2460 元/吨，该合同签订为按照乙方工厂磅单 结算，工厂磅重 537.78 吨，但结算时，按照集装箱北方发运数 538.805 吨进行了结算，差额为 1.025 吨，折合 2460*1.025 吨=2521.5 元，因 JZXYMZSJJM25040 已结算完毕关闭合同，申请 在后续合同 YHYMZSJXS251113002 中扣除该笔货款。 | H81: 其他原因 | I81: 2521.5 | J81: 1.025 | K81: \ | L81: JZXYMZSJJM25040 | M81: 珠三角经营部 | N81: 饲料原料部 | O81: 董典昊 | Y81: =YEAR(C81) -> 2025 | Z81: =MONTH(C81) -> 12 | AA81: =DAY(C81) -> 25
A82: JZXYMFJFZ250084 | B82: 2025年12月4日-2025年12月12日 | C82: 46065 | D82: 商务扣款 | E82: 有关成都东方希望农业有限公司玉米商务扣款事项 | F82: 我司与成都东方希望农业有限公司于 2025 年11月18日签订《粮食销售合同》（合同编号：JZXYMFJFZ250084），数量400吨，单价2440元/吨。该合同已累计提385.33吨，客户2025年12月4日-2025年12月12日接收有3柜出现呕吐毒素超标情况。所提货物匹配计划号：YHSZ-25-092324，新誉库。 经双方友好协商，成都东方希望农业有限公司对该批次货物进行折价接收，以上情况合计产生扣款2345.24元（大写：人民币贰仟叁佰肆拾伍元贰角肆分），该批次累计提货385.33吨，折单吨扣款6.08元/吨，因合同签订保呕吐毒素，前期已加价15元/吨进行销售，可涵盖扣款损失。 | H82: 品质不达标（容重、水分、毒素、蛋白等） | I82: 2345.24 | J82: 83.29 | K82: YHSZ-25-092324，新誉库 | L82: JZXYMFJFZ250084 | M82: 福建经营部 | N82: 饲料原料部 | O82: 许开兴 | X82: 水分 | Y82: =YEAR(C82) -> 2026 | Z82: =MONTH(C82) -> 2 | AA82: =DAY(C82) -> 12
A83: YMZSJDKHWS250040-2 | B83: 46022 | C83: 46030 | D83: 商务扣款 | E83: 温氏集团扣款情况说明 | F83: 2025年12月5日我司与大余温氏畜牧有限公司订内贸玉米转让协议，合同号:YMZSJDKHWS250040-2，数量2000吨，单价2380元/吨，客户提涌港东星海泰078，报 488.7 吨货物杂质( 1.32-1.43)超标，属于折价接收范围，单吨扣价 10元，合计扣款4887 元. | H83: 品质不达标（容重、水分、毒素、蛋白等） | I83: 4887 | J83: 488.7 | K83: 东星海泰/078 | L83: YMZSJDKHWS250040-2 | M83: 珠三角经营部 | N83: 饲料原料部 | O83: 凌梓峰 | X83: 水分 | Y83: =YEAR(C83) -> 2026 | Z83: =MONTH(C83) -> 1 | AA83: =DAY(C83) -> 8
A84: YMZSIDKHWS250038-5 | B84: 46022 | C84: 46030 | D84: 商务扣款 | E84: 温氏集团扣款情况说明 | F84: 2025年12月2日我司与大余温氏畜牧有限公司签订内贸玉米转让协议，协议号:YMZSIDKHWS250038-5，数量1000吨，单价2330元/吨。客户提新港东亿603货物报360.04吨货物杂质(1.36-2.2)超标，属于折价接收范围，单吨扣价10元，合计扣款3600.4元。 | H84: 品质不达标（容重、水分、毒素、蛋白等） | I84: 3600.4 | J84: 360.04 | K84: 东亿603 | L84: YMZSIDKHWS250038-5 | M84: 珠三角经营部 | N84: 饲料原料部 | O84: 凌梓峰 | X84: 水分 | Y84: =YEAR(C84) -> 2026 | Z84: =MONTH(C84) -> 1 | AA84: =DAY(C84) -> 8
A85: YMZSJDKHWS250041-2 | B85: 46022 | C85: 46030 | D85: 商务扣款 | E85: 温氏集团扣款情况说明 | F85: 2025年12月8日我司与广西温氏畜牧有限公司签订内贸玉米合同，协议号YMZSJDKHWS250041-2,数量1650吨，单价2400 元/吨。客户提麻涌港 国家能源 610/2512货物，报375.14吨货物赤霉烯酮(317-1137ppb)超标和水分(15.38-15.41)，属于折价接收范围，单吨扣价 30元，合计扣款 11254.2元 | H85: 品质不达标（容重、水分、毒素、蛋白等） | I85: 11254.2 | J85: 375.14 | K85: 国家能源 610/2512 | L85: YMZSJDKHWS250041-2 | M85: 珠三角经营部 | N85: 饲料原料部 | O85: 凌梓峰 | X85: 水分 | Y85: =YEAR(C85) -> 2026 | Z85: =MONTH(C85) -> 1 | AA85: =DAY(C85) -> 8
A86: YMGXXJ250144 | B86: 46026 | C86: 46035 | D86: 商务扣款 | E86: 关于宾阳通威饲料有限公司内贸玉米商务的说明 | F86: 前期在 2025 年 12 月 8 日与宾阳通威饲料有限公司签署的内贸玉米合同，对应合同号YMGXXJ250144，单价 2465 元/吨，数量 800 吨。于 2025 年 12 月 27 日至 2026 年 1 月 4 日在白沙港“鸿丰 9678”上完成交付（珠三角大船名：国家能源 610/2512），交货数量 779.27 吨。 在实际交货中存在杂质超标情况，其中较为严重的有 5 车，抽检结果为：3-3.3%，通威集团原规定杂质超 2%需供方退货处理，经过友好协商后对这五车做 20 元/吨扣款，数量 199.63 吨，金额为3992.6 元。折算整合同为 5.12 元/吨。 | H86: 品质不达标（容重、水分、毒素、蛋白等） | I86: 3992.6 | J86: 779.27 | K86: 国家能源610/2512 | L86: YMGXXJ250144 | M86: 广西经营部 | N86: 饲料原料部 | O86: 侯霄 | X86: 水分 | Y86: =YEAR(C86) -> 2026 | Z86: =MONTH(C86) -> 1 | AA86: =DAY(C86) -> 13
A87: YMGXXJ250134 | B87: 46383 | C87: 46037 | D87: 商务扣款 | E87: 关于南宁通威生物科技有限公司内贸玉米商务的说明 | F87: 前期在2025年11月17日与南宁通威生物科技有限公司签署的内贸玉米合同，对应合同号 YMGXXJ250134，单价2360元/吨，数量1500吨。于2025年12月23日至2025年12月27日发散船"谢圩6878"配送到厂完成交付(珠三角大船名：国家能源610/2512)，交货数量1492.08吨。 在实际交货中存在水分超标的情况，我司与客户场抽样并邮寄第三方检测机构，实际检测水分为15.69%。经过友好协商后对实际交货数量做17元/吨扣款，数量1492.08吨，金额为25365.36元。 | H87: 品质不达标（容重、水分、毒素、蛋白等） | I87: 25365.36 | J87: 1492.08 | K87: 国家能源610/2512 | L87: YMGXXJ250134 | M87: 广西经营部 | N87: 饲料原料部 | O87: 李戈 | X87: 水分 | Y87: =YEAR(C87) -> 2026 | Z87: =MONTH(C87) -> 1 | AA87: =DAY(C87) -> 15
A88: YMFJFZ250159 | B88: 46346 | C88: 46037 | D88: 商务扣款 | E88: 有关三明海大饲料有限公司玉米商务扣款事项 | F88: 我司与三明海大饲料有限公司于 2025 年11月6日签订《粮食销售合同》（合同编号：YMFJFZ250159），数量500吨，单价2245元/吨。该合同已累计提货494.5吨，客户2025年11月20日-2025年11月22日接收的120.61吨玉米存在毒素超标等情况。所提货物匹配船号：弘泰612/2524。 明细如下： 到厂日期 车号 重量/吨 备注 2025/11/20 闽HB3996 39.16 1906ppb 2025/11/22 闽GA2988 41.30 1350ppb 2025/11/20 闽GA2988 40.15 2406.2ppb 经双方友好协商，三明海大饲料有限公司对该批次货物进行折价接收，以上情况合计产生扣款6195.04元（大写：人民币陆仟壹佰玖拾伍元零角肆分），该批次累计提货120.61吨，折单吨扣款51元/吨。折整批单吨扣款为12.5元/吨，合同签订保呕吐毒素，加价15元/吨。可覆盖扣款。（该订单11月16日申请，当期先款价格2230元/吨，申请2245元/吨签订保毒素交付） 以上扣款是否可行，烦请领导批示，谢谢。 | H88: 品质不达标（容重、水分、毒素、蛋白等） | I88: 6195.04 | J88: 120.61 | K88: 弘泰612/2524 | L88: YMFJFZ250159 | M88: 福建经营部 | N88: 饲料原料部 | O88: 杜宜衡 | X88: 水分 | Y88: =YEAR(C88) -> 2026 | Z88: =MONTH(C88) -> 1 | AA88: =DAY(C88) -> 15
A89: YMFJFZ250134 | B89: 46376 | C89: 46037 | D89: 商务扣款 | E89: 有关深圳市凌念网络科技有限公司玉米商务扣款事项 | F89: 我司与深圳市凌念网络科技有限公司于 2025 年10月23日签订《粮食销售合同》（合同编号：YMFJFZ250134），数量1000吨，单价2260元/吨，约定指标杂质≤1%，呕吐毒素≤1mg/Kg，福州军航码头自提；客户已累计提货985.31 吨。 客户于12月17日-12月19日提货的散粮，存在呕吐超标、杂质超标的情况，合计产生扣款7516.1元（大写：人民币柒仟伍佰壹拾陆元陆角），产生商务扣款货物共计248.53吨，折单吨扣款30.42元/吨。所提货物匹配船名：正海3/2506。（10月23日申请该订单时指导价格为先款2245元/吨，11月马尾港自提）。我司已加价15元/吨进行保毒素销售，溢价可覆盖扣款。 以上扣款是否可行，烦请领导批示，谢谢。 | H89: 品质不达标（容重、水分、毒素、蛋白等） | I89: 7516.1 | J89: 248.53 | K89: 正海3/2506 | L89: YMFJFZ250134 | M89: 福建经营部 | N89: 饲料原料部 | O89: 杜宜衡 | X89: 水分 | Y89: =YEAR(C89) -> 2026 | Z89: =MONTH(C89) -> 1 | AA89: =DAY(C89) -> 15
A90: YMGXQZ250316 | B90: 46030 | C90: 46035 | D90: 商务扣款 | E90: 关于广西园丰牧业集团股份有限公司玉米水分商务扣款 | F90: 与广西园丰牧业集团股份有限公司签订的《粮食销售合同》，合同号：YMGXQZ250316，数量1000吨，单价2415元/吨，提“长峰98/2526”轮散装玉米，其中有6车共200.6吨水分指标远超出合同约定标准15%（合同提前预留有5元/吨商务），客户原则上拒收。经双方协商同意，工厂做商务扣款让步接收，合计扣款金额2679.00元，折合单吨扣款2.68元，溢余2.32元/吨对我司有利。（附商函） | H90: 品质不达标（容重、水分、毒素、蛋白等） | I90: 2679 | J90: 200.6 | K90: “长峰98/2526” | L90: YMGXQZ250316 | M90: 广西经营部 | N90: 饲料原料部 | O90: 杨伟文 | X90: 水分 | Y90: =YEAR(C90) -> 2026 | Z90: =MONTH(C90) -> 1 | AA90: =DAY(C90) -> 13
A91: JZXYMLCYDG251212 | B91: 46033 | C91: 46041 | D91: 商务扣款 | E91: 关于合同号 JZXYMLCYDG251212扣款说明 | F91: 联系单号 YHSZ-25-111428 销售蚌埠丰盛饲料贸易有限公司，2025年12月29 日签订的《粮食销售合同》(合同编号:JZXYMLCYDG251212)合同数量440 吨，合同单价 2450 元/吨。该合同送货过程中-柜运单号ZG25129672602箱号ZGLU3255732杂质偏多，客户需要增加过筛一遍才能处理，经友好协商该柜扣款 20 元/吨让步接收处理 | H91: 品质不达标（容重、水分、毒素、蛋白等） | I91: 547 | J91: 27.35 | L91: JZXYMLCYDG251212 | M91: 珠三角经营部 | N91: 饲料原料部 | O91: 林佳琦 | X91: 水分 | Y91: =YEAR(C91) -> 2026 | Z91: =MONTH(C91) -> 1 | AA91: =DAY(C91) -> 19
A92: YMGXQZ250315 | B92: 46037 | C92: 46037 | D92: 商务扣款 | E92: 关于钦州播恩生物YMGXQZ250315合同商务扣款 | F92: 合同号：YMGXQZ250315，数量600吨，单价2420元/吨，提“长峰98/V2526”轮散装玉米，其中有3车共99.68吨呕吐毒素超出双方约定标准1500（合同多预留有5元/吨商务），客户原则上拒收。经双方协商同意，工厂做商务扣款让步接收，合计扣款金额1324.20元，折合单吨扣款2.20元，溢余2.80元/吨对我司有利。（客户出有商函及检测报告） | H92: 质量问题（霉变、霉味、生虫等） | I92: 1324.2 | J92: 99.68 | K92: “长峰98/V2526” | L92: YMGXQZ250315 | M92: 广西经营部 | N92: 饲料原料部 | O92: 杨伟文 | X92: 霉变 | Y92: =YEAR(C92) -> 2026 | Z92: =MONTH(C92) -> 1 | AA92: =DAY(C92) -> 15
A93: YMZSJJY250195 | B93: 46013 | C93: 46038 | D93: 商务扣款 | E93: 关于 揭阳国雄饲料有限公司YMZSJJY250195合同商务 扣款 | F93: ，2025 年 12 月 11 日签订的《粮食销售合同（赊销）》(合同编号:YMZSJJY250195) 合同数量 1000 吨，合同单价 2415 元/吨，客户提货国翔 3/2540，提货重量 270.82 吨，经检测三车共计 126 吨杂质超出合同约定不符合合同约定标准（杂质≤1.0%），我司承担该批次下超标杂质 126 吨折合货款 1260 元。 经双方友好协商处理后，退货转扣款接收，合计扣款 1260 元 折合 10 元/吨。 | H93: 质量问题（霉变、霉味、生虫等） | I93: 1260 | J93: 126 | K93: 国翔 3/2540 | L93: YMZSJJY250195 扣 | M93: 珠三角经营部 | N93: 饲料原料部 | O93: 蚁毓霖 | X93: 霉变 | Y93: =YEAR(C93) -> 2026 | Z93: =MONTH(C93) -> 1 | AA93: =DAY(C93) -> 16
A94: YMZSJDKHWS250045 | B94: 46015 | C94: 46041 | D94: 商务扣款 | E94: 温氏集团扣款情况说明 | F94: 2025年12月5日我司与 富川广东温氏畜牧有限公司 签订内贸玉米转让协议，合同号YMZSJDKHWS250045 ，数量1000 吨，单价2460元/吨。客户提麻涌港 国家能源610/2512货物，报374.62吨货物赤霉烯酮( 280-483ppb)超标，属于折价接收范围，单吨扣价30元，合计扣款11238.6元。 | H94: 品质不达标（容重、水分、毒素、蛋白等） | I94: 11238.6 | J94: 374.62 | K94: 国家能源 610/2512 | L94: YMZSJDKHWS250045 | M94: 珠三角经营部 | N94: 饲料原料部 | O94: 凌梓峰 | X94: 水分 | Y94: =YEAR(C94) -> 2026 | Z94: =MONTH(C94) -> 1 | AA94: =DAY(C94) -> 19
A95: YMZSJDKHWS250046 | B95: 46015 | C95: 46041 | D95: 商务扣款 | E95: 温氏集团扣款情况说明 | F95: 2025年12月5日 我司与 连州温氏畜牧有限公司 签订内贸玉米合同，协议号：YMZSJDKHWS250046，数量1000吨，单价2460元/吨。客户提麻涌港 国家能源610/2512货物，报192.64吨货物杂质( 1.62)超标，属于折价接收范围，单吨扣价10元，合计扣款1926.4元。 | H95: 质量问题（霉变、霉味、生虫等） | I95: 1926.4 | J95: 192.64 | K95: 国家能源 610/2512 | L95: YMZSJDKHWS250046 | M95: 珠三角经营部 | N95: 饲料原料部 | O95: 凌梓峰 | X95: 霉变 | Y95: =YEAR(C95) -> 2026 | Z95: =MONTH(C95) -> 1 | AA95: =DAY(C95) -> 19
A96: YMZSJXXW260001 | B96: 46037 | C96: 46042 | D96: 商务扣款 | E96: 关于广东嘉好农产品有限公司 YMZSJXXW260001 扣款的请示 | F96: 我司于 2026 年 1 月 5 日与广东嘉好农产品有限公司签订内贸玉米合同，编号 YMZSJXXW260001，数量 1000 吨，单价 2400 元/吨。 客户于南沙港东星海泰/80 提货，提单号 NSDXHT8026021，因工厂检测水分偏高，综合平均水分 15.71%。因对客户成品以及口碑造成影响，扣价 10 元/吨，需扣价:999.38*10=9993.8 元。 | H96: 品质不达标（容重、水分、毒素、蛋白等） | I96: 9993.8 | J96: 999.38 | K96: 东星海泰/080 | L96: YMZSJXXW260001 | M96: 珠三角经营部 | N96: 饲料原料部 | O96: 李长聪 | X96: 水分 | Y96: =YEAR(C96) -> 2026 | Z96: =MONTH(C96) -> 1 | AA96: =DAY(C96) -> 20
A97: YMYXYJ250250-1 | B97: 46036 | C97: 46042 | D97: 商务扣款 | E97: 关于阳春温氏、阳东温氏扣款的说明 | F97: 我司于2025年12月31日与阳江市阳东温氏畜牧有限公司签订了玉米内贸合同YMYXYJ250250-1，签订主体为中粮贸易（深圳）有限公司。合同总量为1000吨，单价为2430元/吨，实际执行量为1013.12吨。大船名：益嘉88/2528。合同约定标准：水分≤15%，赤霉烯酮≤200ppb。1.6-1.9日客户提取了一批玉米（猪料），经检测，其中有330.02吨水分在15.65-15.66之间，赤霉烯酮达到240ppb,不符合合同约定的标准。考虑到双方后期的长期友好合作，对该批货物进行15元/吨的折价处理，折价金额为4950.3元,在货款中扣除。 | H97: 水分≤15%，赤霉烯酮≤200ppb | I97: 4950.3 | J97: 330.02 | K97: 益嘉88/2528 | L97: YMYXYJ250250-1 | M97: 粤西经营部 | N97: 饲料原料部 | O97: 刘佳莹 | X97: 水分 | Y97: =YEAR(C97) -> 2026 | Z97: =MONTH(C97) -> 1 | AA97: =DAY(C97) -> 20
A98: YMYXYJ250250-3 | B98: 46036 | C98: 46042 | D98: 商务扣款 | E98: 关于阳春温氏、阳东温氏扣款的说明 | F98: 我司于2025年12月31日与阳江市阳东温氏畜牧有限公司签订了玉米内贸合同YMYXYJ250250-3，签订主体为中粮贸易（深圳）有限公司。合同总量为1000吨，单价为2430元/吨，实际执行量为1002.32吨。大船名：益嘉88/2528。合同约定标准：水分≤15%，赤霉烯酮≤200ppb，黄曲霉毒素B1（ppb）≤30。1.7-1.8日客户提取了一批玉米（猪料），经检测，其中有317.6吨水分在15.39-15.66之间，赤霉烯酮在318-597之间，黄曲霉毒素达到51，不符合合同约定的标准。考虑到双方后期的长期友好合作，对该批货物进行20元/吨的折价处理，折价金额为6352元，在货款中扣除。 | H98: 水分≤15%，赤霉烯酮≤200ppb，黄曲霉毒素B1（ppb）≤30 | I98: 6352 | J98: 317.6 | K98: 益嘉88/2528 | L98: YMYXYJ250250-3 | M98: 粤西经营部 | N98: 饲料原料部 | O98: 刘佳莹 | X98: 毒素 | Y98: =YEAR(C98) -> 2026 | Z98: =MONTH(C98) -> 1 | AA98: =DAY(C98) -> 20
A99: YMZSJJY250201 | B99: 46024 | C99: 46043 | D99: 商务扣款 | E99: 关于丰顺海新商务扣款 | F99: 丰顺县海新饲料有限公司，2025年 12月 18 日签订《粮食销售合同》(合同编号:YMZSJY250201)，数量500 吨,单价 2390 元/吨,该合同已累计交货497.09 吨,提货锦航佰福/2532(其中1月2日6车车号:粤 BGT302重量 32.02 吨,车号: CC8777,重量 32.23 吨,车号:豫 PU7705,重量 32.26 吨,车号: C4M573,重量 33.14吨，车号:粤 MR7785，重量 33.230 吨，车号:赣 COP948，重量 34.91 吨合计:197.79 吨)到货玉米经检验杂质.2%杂质和破碎粒超出合同约定指标(杂质<1%)，不符合客户接受指标针对该批次到厂不合格玉米。经双方友好协商处理后，退货转扣款接收。合计产生扣款 1977.9元。折合10元/吨 | H99: 杂质.2%杂质和破碎粒超出合同约定指标(杂质<1%) | I99: 1977.9 | J99: 197.79 | K99: 锦航佰福/2532 | L99: YMZSJJY250201) | M99: 珠三角经营部 | N99: 饲料原料部 | O99: 蚁毓霖 | X99: 杂质 | Y99: =YEAR(C99) -> 2026 | Z99: =MONTH(C99) -> 1 | AA99: =DAY(C99) -> 21
A100: YMZSJDGJZX250427 | B100: 46030 | C100: 46043 | D100: 商务扣款 | E100: 关于合同号YMZSJDGJZX250427扣款的请示 | F100: YHSZ-25-111425，台山市向星饲料有限公司，2025年12月11日签订的《粮 食销售合同》(合同编号：YMZSJDGJZX250427)合同数量1080吨，合同单价2472元/吨， 结算数量 1082.09 吨 ，其中10柜，总共267.9吨，因工厂检测抽检发现水份15.19%至 15.62%偏高。不符合合同约定的标准。经过双方友好协商，该10柜按减价4元/吨结算处 理使用，即总共扣款267.9吨*4元/吨=1071.6元 | H100: 品质不达标（容重、水分、毒素、蛋白等） | I100: 1071.6 | J100: 267.9 | L100: YMZSJDGJZX250427 | M100: 珠三角经营部 | N100: 饲料原料部 | O100: 林佳琦 | X100: 水分 | Y100: =YEAR(C100) -> 2026 | Z100: =MONTH(C100) -> 1 | AA100: =DAY(C100) -> 21
...

Sheet 联系单模版
A1: 联系单编号： | B1: JZXYMZSJJM26001
A2: 中粮贸易沿海大区工作联系单
A3: 发出部门 | B3: =VLOOKUP(B1,流程!A:O,12,FALSE) -> JZXYMZSJJM26001 | D3: 接收部门 | E3: =VLOOKUP(B1,流程!A:P,13,FALSE) -> 珠三角经营部
A4: 主题 | B4: =VLOOKUP(B1,流程!A:G,5,FALSE) -> 关于开平市绿皇JZXYMZSJJM26001合同商务扣款
A5: =VLOOKUP(B1,流程!A:H,6,FALSE) -> YHSZ-25-121919、开平市绿皇农牧发展有限公司，2026年1月6日签订的《粮食销售合同》（合同编号：JZXYMZSJJM26001）合同数量1030吨，合同单价2450元/吨，结算数量1018.14，其中3柜，总共76.53吨，因工厂仓库收货开柜后发现玉米有霉味的现象，经过协商沟通，进行扣款处理。（1）车号:湘U6955,柜号:XYLU1191171，来货实收重量:21.55吨。（2）车号:湘MJ9132,柜号:XYLU1178631，来货实收重量:27.98吨。（3）车号:湘LD6811,柜号:XYLU1313449，来货实收重量:27吨。合计:76.53*20=1530.6元
A6: 发起人 | C6: =VLOOKUP(B1,流程!A:R,15,FALSE) -> 汤妮 | E6: =VLOOKUP(B1,流程!A:S,16,FALSE) -> 珠三角经营部

Sheet 字段列表
A2: 费用原因分类
A3: 质量问题（霉变、霉味、生虫等）
A4: 物流发运与计划不符
A5: 发运集中到货
A6: 库存前移未及时销售
A7: 流程手续问题
A8: 客户仓容有限提货慢
A9: 包装破损、水湿、短重等
A10: 品质不达标（容重、水分、毒素、蛋白等）
A11: 其他原因
